adsr/adsr.v
/* ===================
 * Envelope generator
 * ===================
 *
 * Creates an 8-bit ADSR (attack, decay, sustain, release) volume envelope.
 *
 *        ..
 *     A . `. D    S
 *      .    `----------
 *     .                . R
 *    .                  `  .
 *  ---------------------------->
 *                             t
 
 даже если работать на частоте 44100,
 и прибавлять минимальное значение - 1.
 то период не будет длиннее 2х секунд при 16 битах.

 https://docs.google.com/spreadsheets/d/1mJjj54YKQSbWEbEiOg4bpXEgip-hPy3FrPeEfphbzk0/edit?gid=1902719290#gid=1902719290

поэтому решено аккумулятор для ADSR примернять 24 бита
и субдискр - 48000. 
 */
module adsr #(
		parameter SAMPLE_CLK_FREQ = 48000,
		parameter MASTER_CLK_FREQ = 50000000,
		parameter WIDTH = 8,
		parameter CTRL_WIDTH = 4,
		parameter ACCUMULATOR_BITS = 24

	)
	(
		clk, rst, low_strobe, gate, a, d, s, r, signal_out
	);

	input wire clk, rst, low_strobe;
	output wire [(ACCUMULATOR_BITS - 1):0] signal_out;

	input wire gate;
	input wire [(CTRL_WIDTH-1):0] a;
	input wire [(CTRL_WIDTH-1):0] d;
	input wire [(CTRL_WIDTH-1):0] s;
	input wire [(CTRL_WIDTH-1):0] r;

	assign signal_out = accumulator;

	localparam  ACCUMULATOR_SIZE = 2**ACCUMULATOR_BITS;
	localparam  ACCUMULATOR_MAX  = ACCUMULATOR_SIZE-1;

	reg [ACCUMULATOR_BITS-1:0] accumulator;

	localparam OFF     = 3'd0;
	localparam ATTACK  = 3'd1;
	localparam DECAY   = 3'd2;
	localparam SUSTAIN = 3'd3;
	localparam RELEASE = 3'd4;


	reg[2:0] state;

	`define CALCULATE_PHASE_INCREMENT(n) $rtoi(ACCUMULATOR_SIZE / (n * SAMPLE_CLK_FREQ))

	initial begin
		state <= OFF;
		accumulator = 0;
	end

	function [(ACCUMULATOR_BITS - 1):0] attack_table;
		input [(CTRL_WIDTH-1):0] param;
		begin
			case(param)
				4'b0000: attack_table = `CALCULATE_PHASE_INCREMENT(0.002); //0.002 
				4'b0001: attack_table = `CALCULATE_PHASE_INCREMENT(0.008);
				4'b0010: attack_table = `CALCULATE_PHASE_INCREMENT(0.016);
				4'b0011: attack_table = `CALCULATE_PHASE_INCREMENT(0.024);
				4'b0100: attack_table = `CALCULATE_PHASE_INCREMENT(0.038);
				4'b0101: attack_table = `CALCULATE_PHASE_INCREMENT(0.056);
				4'b0110: attack_table = `CALCULATE_PHASE_INCREMENT(0.068);
				4'b0111: attack_table = `CALCULATE_PHASE_INCREMENT(0.080);
				4'b1000: attack_table = `CALCULATE_PHASE_INCREMENT(0.100);
				4'b1001: attack_table = `CALCULATE_PHASE_INCREMENT(0.250);
				4'b1010: attack_table = `CALCULATE_PHASE_INCREMENT(0.500);
				4'b1011: attack_table = `CALCULATE_PHASE_INCREMENT(0.800);
				4'b1100: attack_table = `CALCULATE_PHASE_INCREMENT(1.000);
				4'b1101: attack_table = `CALCULATE_PHASE_INCREMENT(3.000);
				4'b1110: attack_table = `CALCULATE_PHASE_INCREMENT(5.000);
				4'b1111: attack_table = `CALCULATE_PHASE_INCREMENT(8.000);
				default: attack_table = 65535;
			endcase
		end
	endfunction

	function [(ACCUMULATOR_BITS - 1):0] decay_release_table;
		input [(CTRL_WIDTH-1):0] param;
		begin
			case(param)
				4'b0000: decay_release_table = `CALCULATE_PHASE_INCREMENT(0.006); //0.006
				4'b0001: decay_release_table = `CALCULATE_PHASE_INCREMENT(0.024);
				4'b0010: decay_release_table = `CALCULATE_PHASE_INCREMENT(0.048);
				4'b0011: decay_release_table = `CALCULATE_PHASE_INCREMENT(0.072);
				4'b0100: decay_release_table = `CALCULATE_PHASE_INCREMENT(0.114);
				4'b0101: decay_release_table = `CALCULATE_PHASE_INCREMENT(0.168);
				4'b0110: decay_release_table = `CALCULATE_PHASE_INCREMENT(0.204);
				4'b0111: decay_release_table = `CALCULATE_PHASE_INCREMENT(0.240);
				4'b1000: decay_release_table = `CALCULATE_PHASE_INCREMENT(0.300);
				4'b1001: decay_release_table = `CALCULATE_PHASE_INCREMENT(0.750);
				4'b1010: decay_release_table = `CALCULATE_PHASE_INCREMENT(1.500);
				4'b1011: decay_release_table = `CALCULATE_PHASE_INCREMENT(2.400);
				4'b1100: decay_release_table = `CALCULATE_PHASE_INCREMENT(3.000);
				4'b1101: decay_release_table = `CALCULATE_PHASE_INCREMENT(9.000);
				4'b1110: decay_release_table = `CALCULATE_PHASE_INCREMENT(15.00);
				4'b1111: decay_release_table = `CALCULATE_PHASE_INCREMENT(24.00);
				default: decay_release_table = 65535;
			endcase
		end
	endfunction


	// value to add to accumulator during attack phase
	// calculated from lookup table below based on attack parameter
	reg [(ACCUMULATOR_BITS - 1):0] attack_step;
	always @(a) begin
		attack_step <= attack_table(a); // convert 4-bit value into phase increment amount
	end

	// value to add to accumulator during decay phase
	// calculated from lookup table below based on decay parameter
	reg [(ACCUMULATOR_BITS - 1):0] decay_step;
	always @(d) begin
		decay_step <= decay_release_table(d); // convert 4-bit value into phase increment amount
	end

	
	reg [(ACCUMULATOR_BITS - 1):0] release_inc;
	always @(r) begin
		release_inc <= decay_release_table(r); // convert 4-bit value into phase increment amount
	end


	wire [ACCUMULATOR_BITS-1:0] next_acc_inc = accumulator + attack_step;
	wire [ACCUMULATOR_BITS-1:0] next_acc_dec = accumulator - decay_step;

	wire [ACCUMULATOR_BITS-1:0] sustain_volume;
	assign sustain_volume = s << (ACCUMULATOR_BITS - CTRL_WIDTH);

	assign overflow_max = accumulator > next_acc_inc;
	assign overflow_min = accumulator < next_acc_dec;
	assign upderflow_sust = accumulator < sustain_volume;

	always @(posedge clk) begin
		case (state)
			OFF:
				begin
					if ( gate == 1'b0 ) begin
						state <= OFF;
					end else begin
						if (overflow_max) begin
							state <= RELEASE;
						end else begin
							state <= ATTACK;
							if (low_strobe) begin
								accumulator <= next_acc_inc;
							end else begin
								accumulator <= accumulator;
							end
						end
					end
				end
			ATTACK:
				begin
					if ( gate == 1'b0 ) begin
						state <= RELEASE;
					end else begin
						if (overflow_max) begin
							state <= DECAY;
						end else begin
							if (low_strobe) begin
								accumulator <= next_acc_inc;
							end else begin
								accumulator <= accumulator;
							end
						end
					end
				end
			DECAY:
				begin
					if ( gate == 1'b0 ) begin
						state <= RELEASE;
					end else begin
						if (upderflow_sust) begin
							state <= SUSTAIN;
						end else begin
							if (low_strobe) begin
								accumulator <= next_acc_dec;
							end else begin
								accumulator <= accumulator;
							end
						end
					end
				end
			SUSTAIN:
				begin
					if ( gate == 1'b0 ) begin
						state <= RELEASE;
					end
				end
			RELEASE:
				begin
					if ( gate == 1'b0 ) begin
						if (overflow_min) begin
							state <= OFF;
							accumulator <= 0;
						end else begin
							accumulator <= next_acc_dec;
						end
					end else begin
						state <= ATTACK;
					end
				end
		endcase
	end

endmodule

powerup_reset/powerup_reset.v
module powerup_reset(key, clk, rst);
	parameter TICK = 4'd15; // tick's delay 0..15
			
	input wire key;
	input wire clk;
	output reg rst;
			
	reg [3:0] tick_timer;

	initial begin
		rst <= 1;
		tick_timer <= TICK;
	end
		
	always @(posedge clk) begin
		if (key) begin
			tick_timer <= TICK;
			rst <= 1;
		end else begin
			if (tick_timer==4'd0) begin
				rst <= 0;
			end else begin
				tick_timer <= tick_timer - 1'b1;
			end
		end
	end
endmodule

common/strobe_gen.v
module strobe_gen(clk, f, signal_out);
		
	input wire f;
	input wire clk;
	output wire signal_out;
			
	reg prev;

	initial begin
		prev <= 1'b0;
	end
		
	always @(posedge clk) begin
		prev <= f;
	end

    assign signal_out = ((f==1'b1)&&(prev==1'b0));
endmodule

common/frqdivmod.v
module frqdivmod(clk, signal_out);
parameter DIV=2;
// calculated parameters
parameter WITH = ($clog2(DIV+1)>0) ? $clog2(DIV+1) : 1;

input wire clk;
output wire signal_out;

reg clk_n; 

reg [(WITH-1):0] pos_cnt; 
reg [(WITH-1):0] neg_cnt; 

wire [(WITH-1):0] div_value = DIV[(WITH-1):0];

initial begin
	clk_n <= 1'b0;
	pos_cnt <= {(WITH){1'b0}};
	neg_cnt <= {(WITH){1'b0}};
end

assign signal_out = (DIV==1) ? clk : clk_n;

always @ (posedge clk) begin
	pos_cnt <= (pos_cnt + 1'b1) % div_value;
end

always @ (negedge clk) begin
	neg_cnt <= (neg_cnt + 1'b1) % div_value;
end

always @(clk, pos_cnt, neg_cnt) begin //pos_cnt in sens list addd for resolve warning "variable is read inside the Always Construct but isn't in the Always Construct's Event Control"
	if ((DIV%2) == 1'b0) begin
		clk_n <= ( pos_cnt >= (DIV/2)) ? 1'b1 : 1'b0;
	end else begin
		clk_n <= (( pos_cnt > (DIV/2)) || ( neg_cnt > (DIV/2))) ? 1'b1 : 1'b0;
	end
end
	
endmodule

adsr/test/testbench.v
`timescale 1ns / 1ps

module testbench();
  parameter TEST_DURATION = 1000000;

  wire rst;
  wire signal_out_2;
  wire [23:0] signal_out_3;
  reg key0;
  initial key0 <= 0;

  reg clk50M;
  initial clk50M <= 0;
  always
    #10 clk50M <= ~clk50M; // Задержка 10 ns (100mhz -  50 mhz clk)

  // 50M / 48000 = 1041.66666667
  frqdivmod #(.DIV(1042)) frqdivmod_48000(
    .clk(clk50M),
    .signal_out(signal_out_2)
  );

  wire signal_48strobe;

  strobe_gen strobe_gen_48(
    .clk(clk50M),
    .f(signal_out_2),
    .signal_out(signal_48strobe)
  );


  // генератор сброса
  powerup_reset res_gen(
    .clk(clk50M),
    .key(key0),
    .rst(rst)
  );

  reg [7:0] log_reg;
  initial log_reg <= 0;

  reg [7:0] lookup_table [0:255];
  initial begin
      $readmemh("../exp.rom", lookup_table); // Загрузка таблицы из файла
  end

  always @ (posedge clk50M) begin
    log_reg <= log_reg + 1'b1;
  end

  wire [0:255] dout;
  assign dout = lookup_table[log_reg];

	reg [3:0] a;
	reg [3:0] d;
	reg [3:0] s;
	reg [3:0] r;
	reg gate;
  reg wft;

  initial a <= 4'b0000;
  initial d <= 0;
  initial s <= 4'b0111;
  initial r <= 0;
  initial gate <= 0;
  initial wft <=1;

  adsr adsr_1(
    .clk(clk50M),
    // .low_strobe(signal_48strobe), // ТЕСТ 48000
    .low_strobe(wft || signal_48strobe), // ТЕСТ ВОЛНОФОРМ
    .rst(rst),
    .gate(gate),
    .a(a), .d(d), .s(s), .r(r),
    .signal_out(signal_out_3)
  );

  initial
  begin
    #1000 gate <= 1;
    #10000 gate <= 0;
  
    #5000 gate <= 1;
    #1500 gate <= 0;

    #5000 gate <= 1;
    #3000 gate <= 0;
    #200 gate <= 1;
    #200 gate <= 0;

    #10000 gate <= 1;
    #10000 gate <= 0;
    #1200 gate <= 1;
    #200 gate <= 0;


    #10000 gate <= 1; wft <=0;
    #5000 a <= 0; d <= 0;
    #5000 a <= 1; d <= 1;
    #5000 a <= 2; d <= 2;
    #5000 a <= 3; d <= 3;
    #5000 a <= 4; d <= 4;
    #5000 a <= 5; d <= 5;
    #5000 a <= 6; d <= 6;
    #5000 a <= 7; d <= 7;
    #5000 a <= 8; d <= 8;
    #5000 a <= 9; d <= 9;
    #5000 a <= 10; d <= 10;
    #5000 a <= 11; d <= 11;
    #5000 a <= 12; d <= 12;
    #5000 a <= 13; d <= 13;
    #5000 a <= 14; d <= 14;
    #5000 a <= 15; d <= 15;


  end

  initial
  begin
    $dumpfile("out.vcd");
    $dumpvars(0,testbench);

    #TEST_DURATION;
    $display("test completed.");
    $finish;
  end
endmodule

adsr/test/out.vcd
$date
	Wed Apr 16 14:02:54 2025
$end
$version
	Icarus Verilog
$end
$timescale
	1ps
$end
$scope module testbench $end
$var wire 24 ! signal_out_3 [23:0] $end
$var wire 1 " signal_out_2 $end
$var wire 1 # signal_48strobe $end
$var wire 1 $ rst $end
$var wire 256 % dout [0:255] $end
$var parameter 32 & TEST_DURATION $end
$var reg 4 ' a [3:0] $end
$var reg 1 ( clk50M $end
$var reg 4 ) d [3:0] $end
$var reg 1 * gate $end
$var reg 1 + key0 $end
$var reg 8 , log_reg [7:0] $end
$var reg 4 - r [3:0] $end
$var reg 4 . s [3:0] $end
$var reg 1 / wft $end
$scope module adsr_1 $end
$var wire 4 0 a [3:0] $end
$var wire 1 ( clk $end
$var wire 4 1 d [3:0] $end
$var wire 1 * gate $end
$var wire 1 2 low_strobe $end
$var wire 4 3 r [3:0] $end
$var wire 4 4 s [3:0] $end
$var wire 24 5 signal_out [23:0] $end
$var wire 1 6 upderflow_sust $end
$var wire 24 7 sustain_volume [23:0] $end
$var wire 1 $ rst $end
$var wire 1 8 overflow_min $end
$var wire 1 9 overflow_max $end
$var wire 24 : next_acc_inc [23:0] $end
$var wire 24 ; next_acc_dec [23:0] $end
$var parameter 32 < ACCUMULATOR_BITS $end
$var parameter 33 = ACCUMULATOR_MAX $end
$var parameter 32 > ACCUMULATOR_SIZE $end
$var parameter 3 ? ATTACK $end
$var parameter 32 @ CTRL_WIDTH $end
$var parameter 3 A DECAY $end
$var parameter 32 B MASTER_CLK_FREQ $end
$var parameter 3 C OFF $end
$var parameter 3 D RELEASE $end
$var parameter 32 E SAMPLE_CLK_FREQ $end
$var parameter 3 F SUSTAIN $end
$var parameter 32 G WIDTH $end
$var reg 24 H accumulator [23:0] $end
$var reg 24 I attack_step [23:0] $end
$var reg 24 J decay_step [23:0] $end
$var reg 24 K release_inc [23:0] $end
$var reg 3 L state [2:0] $end
$scope function attack_table $end
$var reg 4 M param [3:0] $end
$upscope $end
$scope function decay_release_table $end
$var reg 4 N param [3:0] $end
$upscope $end
$upscope $end
$scope module frqdivmod_48000 $end
$var wire 1 ( clk $end
$var wire 11 O div_value [10:0] $end
$var wire 1 " signal_out $end
$var parameter 32 P DIV $end
$var parameter 32 Q WITH $end
$var reg 1 " clk_n $end
$var reg 11 R neg_cnt [10:0] $end
$var reg 11 S pos_cnt [10:0] $end
$upscope $end
$scope module res_gen $end
$var wire 1 ( clk $end
$var wire 1 + key $end
$var parameter 4 T TICK $end
$var reg 1 $ rst $end
$var reg 4 U tick_timer [3:0] $end
$upscope $end
$scope module strobe_gen_48 $end
$var wire 1 ( clk $end
$var wire 1 " f $end
$var wire 1 # signal_out $end
$var reg 1 V prev $end
$upscope $end
$upscope $end
$enddefinitions $end
$comment Show the parameter values. $end
$dumpall
b1111 T
b1011 Q
b10000010010 P
b1000 G
b11 F
b1011101110000000 E
b100 D
b0 C
b10111110101111000010000000 B
b10 A
b100 @
b1 ?
b1000000000000000000000000 >
b111111111111111111111111 =
b11000 <
b11110100001001000000 &
$end
#0
$dumpvars
0V
b1111 U
b0 S
b1 R
b10000010010 O
b0 N
b0 M
b0 L
b1110001110001110 K
b1110001110001110 J
b101010101010101010 I
b0 H
b111111110001110001110010 ;
b101010101010101010 :
09
18
b11100000000000000000000 7
16
b0 5
b111 4
b0 3
12
b0 1
b0 0
1/
b111 .
b0 -
b0 ,
0+
0*
b0 )
0(
b0 '
b11111111 %
1$
0#
0"
b0 !
$end
#10000
b1 S
b1110 U
b11111001 %
b1 ,
1(
#20000
b10 R
0(
#30000
b11110100 %
b10 ,
b1101 U
b10 S
1(
#40000
b11 R
0(
#50000
b11 S
b1100 U
b11101110 %
b11 ,
1(
#60000
b100 R
0(
#70000
b11101001 %
b100 ,
b1011 U
b100 S
1(
#80000
b101 R
0(
#90000
b101 S
b1010 U
b11100100 %
b101 ,
1(
#100000
b110 R
0(
#110000
b11011111 %
b110 ,
b1001 U
b110 S
1(
#120000
b111 R
0(
#130000
b111 S
b1000 U
b11011010 %
b111 ,
1(
#140000
b1000 R
0(
#150000
b11010110 %
b1000 ,
b111 U
b1000 S
1(
#160000
b1001 R
0(
#170000
b1001 S
b110 U
b11010001 %
b1001 ,
1(
#180000
b1010 R
0(
#190000
b11001101 %
b1010 ,
b101 U
b1010 S
1(
#200000
b1011 R
0(
#210000
b1011 S
b100 U
b11001000 %
b1011 ,
1(
#220000
b1100 R
0(
#230000
b11000100 %
b1100 ,
b11 U
b1100 S
1(
#240000
b1101 R
0(
#250000
b1101 S
b10 U
b11000000 %
b1101 ,
1(
#260000
b1110 R
0(
#270000
b10111011 %
b1110 ,
b1 U
b1110 S
1(
#280000
b1111 R
0(
#290000
b1111 S
b0 U
b10110111 %
b1111 ,
1(
#300000
b10000 R
0(
#310000
b10110011 %
b10000 ,
0$
b10000 S
1(
#320000
b10001 R
0(
#330000
b10001 S
b10110000 %
b10001 ,
1(
#340000
b10010 R
0(
#350000
b10101100 %
b10010 ,
b10010 S
1(
#360000
b10011 R
0(
#370000
b10011 S
b10101000 %
b10011 ,
1(
#380000
b10100 R
0(
#390000
b10100100 %
b10100 ,
b10100 S
1(
#400000
b10101 R
0(
#410000
b10101 S
b10100001 %
b10101 ,
1(
#420000
b10110 R
0(
#430000
b10011101 %
b10110 ,
b10110 S
1(
#440000
b10111 R
0(
#450000
b10111 S
b10011010 %
b10111 ,
1(
#460000
b11000 R
0(
#470000
b10010111 %
b11000 ,
b11000 S
1(
#480000
b11001 R
0(
#490000
b11001 S
b10010011 %
b11001 ,
1(
#500000
b11010 R
0(
#510000
b10010000 %
b11010 ,
b11010 S
1(
#520000
b11011 R
0(
#530000
b11011 S
b10001101 %
b11011 ,
1(
#540000
b11100 R
0(
#550000
b10001010 %
b11100 ,
b11100 S
1(
#560000
b11101 R
0(
#570000
b11101 S
b10000111 %
b11101 ,
1(
#580000
b11110 R
0(
#590000
b10000100 %
b11110 ,
b11110 S
1(
#600000
b11111 R
0(
#610000
b11111 S
b10000001 %
b11111 ,
1(
#620000
b100000 R
0(
#630000
b1111110 %
b100000 ,
b100000 S
1(
#640000
b100001 R
0(
#650000
b100001 S
b1111100 %
b100001 ,
1(
#660000
b100010 R
0(
#670000
b1111001 %
b100010 ,
b100010 S
1(
#680000
b100011 R
0(
#690000
b100011 S
b1110110 %
b100011 ,
1(
#700000
b100100 R
0(
#710000
b1110100 %
b100100 ,
b100100 S
1(
#720000
b100101 R
0(
#730000
b100101 S
b1110001 %
b100101 ,
1(
#740000
b100110 R
0(
#750000
b1101111 %
b100110 ,
b100110 S
1(
#760000
b100111 R
0(
#770000
b100111 S
b1101101 %
b100111 ,
1(
#780000
b101000 R
0(
#790000
b1101010 %
b101000 ,
b101000 S
1(
#800000
b101001 R
0(
#810000
b101001 S
b1101000 %
b101001 ,
1(
#820000
b101010 R
0(
#830000
b1100110 %
b101010 ,
b101010 S
1(
#840000
b101011 R
0(
#850000
b101011 S
b1100011 %
b101011 ,
1(
#860000
b101100 R
0(
#870000
b1100001 %
b101100 ,
b101100 S
1(
#880000
b101101 R
0(
#890000
b101101 S
b1011111 %
b101101 ,
1(
#900000
b101110 R
0(
#910000
b1011101 %
b101110 ,
b101110 S
1(
#920000
b101111 R
0(
#930000
b101111 S
b1011011 %
b101111 ,
1(
#940000
b110000 R
0(
#950000
b1011001 %
b110000 ,
b110000 S
1(
#960000
b110001 R
0(
#970000
b110001 S
b1010111 %
b110001 ,
1(
#980000
b110010 R
0(
#990000
b1010101 %
b110010 ,
b110010 S
1(
#1000000
b110011 R
0(
1*
#1010000
b110011 S
b1010101010101010100 :
08
b11100011100011100 ;
b101010101010101010 !
b101010101010101010 5
b101010101010101010 H
b1 L
b1010011 %
b110011 ,
1(
#1020000
b110100 R
0(
#1030000
b1010010 %
b110100 ,
b1111111111111111110 :
b1000111000111000110 ;
b1010101010101010100 !
b1010101010101010100 5
b1010101010101010100 H
b110100 S
1(
#1040000
b110101 R
0(
#1050000
b110101 S
b10101010101010101000 :
b1110001110001110000 ;
b1111111111111111110 !
b1111111111111111110 5
b1111111111111111110 H
b1010000 %
b110101 ,
1(
#1060000
b110110 R
0(
#1070000
b1001110 %
b110110 ,
b11010101010101010010 :
b10011100011100011010 ;
b10101010101010101000 !
b10101010101010101000 5
b10101010101010101000 H
b110110 S
1(
#1080000
b110111 R
0(
#1090000
b110111 S
b11111111111111111100 :
b11000111000111000100 ;
b11010101010101010010 !
b11010101010101010010 5
b11010101010101010010 H
b1001100 %
b110111 ,
1(
#1100000
b111000 R
0(
#1110000
b1001011 %
b111000 ,
b100101010101010100110 :
b11110001110001101110 ;
b11111111111111111100 !
b11111111111111111100 5
b11111111111111111100 H
b111000 S
1(
#1120000
b111001 R
0(
#1130000
b111001 S
b101010101010101010000 :
b100011100011100011000 ;
b100101010101010100110 !
b100101010101010100110 5
b100101010101010100110 H
b1001001 %
b111001 ,
1(
#1140000
b111010 R
0(
#1150000
b1001000 %
b111010 ,
b101111111111111111010 :
b101000111000111000010 ;
b101010101010101010000 !
b101010101010101010000 5
b101010101010101010000 H
b111010 S
1(
#1160000
b111011 R
0(
#1170000
b111011 S
b110101010101010100100 :
b101110001110001101100 ;
b101111111111111111010 !
b101111111111111111010 5
b101111111111111111010 H
b1000110 %
b111011 ,
1(
#1180000
b111100 R
0(
#1190000
b1000100 %
b111100 ,
b111010101010101001110 :
b110011100011100010110 ;
b110101010101010100100 !
b110101010101010100100 5
b110101010101010100100 H
b111100 S
1(
#1200000
b111101 R
0(
#1210000
b111101 S
b111111111111111111000 :
b111000111000111000000 ;
b111010101010101001110 !
b111010101010101001110 5
b111010101010101001110 H
b1000011 %
b111101 ,
1(
#1220000
b111110 R
0(
#1230000
b1000010 %
b111110 ,
b1000101010101010100010 :
b111110001110001101010 ;
b111111111111111111000 !
b111111111111111111000 5
b111111111111111111000 H
b111110 S
1(
#1240000
b111111 R
0(
#1250000
b111111 S
b1001010101010101001100 :
b1000011100011100010100 ;
b1000101010101010100010 !
b1000101010101010100010 5
b1000101010101010100010 H
b1000000 %
b111111 ,
1(
#1260000
b1000000 R
0(
#1270000
b111111 %
b1000000 ,
b1001111111111111110110 :
b1001000111000110111110 ;
b1001010101010101001100 !
b1001010101010101001100 5
b1001010101010101001100 H
b1000000 S
1(
#1280000
b1000001 R
0(
#1290000
b1000001 S
b1010101010101010100000 :
b1001110001110001101000 ;
b1001111111111111110110 !
b1001111111111111110110 5
b1001111111111111110110 H
b111101 %
b1000001 ,
1(
#1300000
b1000010 R
0(
#1310000
b111100 %
b1000010 ,
b1011010101010101001010 :
b1010011100011100010010 ;
b1010101010101010100000 !
b1010101010101010100000 5
b1010101010101010100000 H
b1000010 S
1(
#1320000
b1000011 R
0(
#1330000
b1000011 S
b1011111111111111110100 :
b1011000111000110111100 ;
b1011010101010101001010 !
b1011010101010101001010 5
b1011010101010101001010 H
b111011 %
b1000011 ,
1(
#1340000
b1000100 R
0(
#1350000
b111001 %
b1000100 ,
b1100101010101010011110 :
b1011110001110001100110 ;
b1011111111111111110100 !
b1011111111111111110100 5
b1011111111111111110100 H
b1000100 S
1(
#1360000
b1000101 R
0(
#1370000
b1000101 S
b1101010101010101001000 :
b1100011100011100010000 ;
b1100101010101010011110 !
b1100101010101010011110 5
b1100101010101010011110 H
b111000 %
b1000101 ,
1(
#1380000
b1000110 R
0(
#1390000
b110111 %
b1000110 ,
b1101111111111111110010 :
b1101000111000110111010 ;
b1101010101010101001000 !
b1101010101010101001000 5
b1101010101010101001000 H
b1000110 S
1(
#1400000
b1000111 R
0(
#1410000
b1000111 S
b1110101010101010011100 :
b1101110001110001100100 ;
b1101111111111111110010 !
b1101111111111111110010 5
b1101111111111111110010 H
b110110 %
b1000111 ,
1(
#1420000
b1001000 R
0(
#1430000
b110101 %
b1001000 ,
b1111010101010101000110 :
b1110011100011100001110 ;
b1110101010101010011100 !
b1110101010101010011100 5
b1110101010101010011100 H
b1001000 S
1(
#1440000
b1001001 R
0(
#1450000
b1001001 S
b1111111111111111110000 :
b1111000111000110111000 ;
b1111010101010101000110 !
b1111010101010101000110 5
b1111010101010101000110 H
b110011 %
b1001001 ,
1(
#1460000
b1001010 R
0(
#1470000
b110010 %
b1001010 ,
b10000101010101010011010 :
b1111110001110001100010 ;
b1111111111111111110000 !
b1111111111111111110000 5
b1111111111111111110000 H
b1001010 S
1(
#1480000
b1001011 R
0(
#1490000
b1001011 S
b10001010101010101000100 :
b10000011100011100001100 ;
b10000101010101010011010 !
b10000101010101010011010 5
b10000101010101010011010 H
b110001 %
b1001011 ,
1(
#1500000
b1001100 R
0(
#1510000
b110000 %
b1001100 ,
b10001111111111111101110 :
b10001000111000110110110 ;
b10001010101010101000100 !
b10001010101010101000100 5
b10001010101010101000100 H
b1001100 S
1(
#1520000
b1001101 R
0(
#1530000
b1001101 S
b10010101010101010011000 :
b10001110001110001100000 ;
b10001111111111111101110 !
b10001111111111111101110 5
b10001111111111111101110 H
b101111 %
b1001101 ,
1(
#1540000
b1001110 R
0(
#1550000
b101110 %
b1001110 ,
b10011010101010101000010 :
b10010011100011100001010 ;
b10010101010101010011000 !
b10010101010101010011000 5
b10010101010101010011000 H
b1001110 S
1(
#1560000
b1001111 R
0(
#1570000
b1001111 S
b10011111111111111101100 :
b10011000111000110110100 ;
b10011010101010101000010 !
b10011010101010101000010 5
b10011010101010101000010 H
b101101 %
b1001111 ,
1(
#1580000
b1010000 R
0(
#1590000
b101100 %
b1010000 ,
b10100101010101010010110 :
b10011110001110001011110 ;
b10011111111111111101100 !
b10011111111111111101100 5
b10011111111111111101100 H
b1010000 S
1(
#1600000
b1010001 R
0(
#1610000
b1010001 S
b10101010101010101000000 :
b10100011100011100001000 ;
b10100101010101010010110 !
b10100101010101010010110 5
b10100101010101010010110 H
b101011 %
b1010001 ,
1(
#1620000
b1010010 R
0(
#1630000
b101010 %
b1010010 ,
b10101111111111111101010 :
b10101000111000110110010 ;
b10101010101010101000000 !
b10101010101010101000000 5
b10101010101010101000000 H
b1010010 S
1(
#1640000
b1010011 R
0(
#1650000
b1010011 S
b10110101010101010010100 :
b10101110001110001011100 ;
b10101111111111111101010 !
b10101111111111111101010 5
b10101111111111111101010 H
b101001 %
b1010011 ,
1(
#1660000
b1010100 R
0(
#1670000
b101000 %
b1010100 ,
b10111010101010100111110 :
b10110011100011100000110 ;
b10110101010101010010100 !
b10110101010101010010100 5
b10110101010101010010100 H
b1010100 S
1(
#1680000
b1010101 R
0(
#1690000
b1010101 S
b10111111111111111101000 :
b10111000111000110110000 ;
b10111010101010100111110 !
b10111010101010100111110 5
b10111010101010100111110 H
b1010101 ,
1(
#1700000
b1010110 R
0(
#1710000
b100111 %
b1010110 ,
b11000101010101010010010 :
b10111110001110001011010 ;
b10111111111111111101000 !
b10111111111111111101000 5
b10111111111111111101000 H
b1010110 S
1(
#1720000
b1010111 R
0(
#1730000
b1010111 S
b11001010101010100111100 :
b11000011100011100000100 ;
b11000101010101010010010 !
b11000101010101010010010 5
b11000101010101010010010 H
b100110 %
b1010111 ,
1(
#1740000
b1011000 R
0(
#1750000
b100101 %
b1011000 ,
b11001111111111111100110 :
b11001000111000110101110 ;
b11001010101010100111100 !
b11001010101010100111100 5
b11001010101010100111100 H
b1011000 S
1(
#1760000
b1011001 R
0(
#1770000
b1011001 S
b11010101010101010010000 :
b11001110001110001011000 ;
b11001111111111111100110 !
b11001111111111111100110 5
b11001111111111111100110 H
b100100 %
b1011001 ,
1(
#1780000
b1011010 R
0(
#1790000
b100011 %
b1011010 ,
b11011010101010100111010 :
b11010011100011100000010 ;
b11010101010101010010000 !
b11010101010101010010000 5
b11010101010101010010000 H
b1011010 S
1(
#1800000
b1011011 R
0(
#1810000
b1011011 S
b11011111111111111100100 :
b11011000111000110101100 ;
b11011010101010100111010 !
b11011010101010100111010 5
b11011010101010100111010 H
b1011011 ,
1(
#1820000
b1011100 R
0(
#1830000
b100010 %
b1011100 ,
b11100101010101010001110 :
b11011110001110001010110 ;
b11011111111111111100100 !
b11011111111111111100100 5
b11011111111111111100100 H
b1011100 S
1(
#1840000
b1011101 R
0(
#1850000
b1011101 S
b11101010101010100111000 :
b11100011100011100000000 ;
06
b11100101010101010001110 !
b11100101010101010001110 5
b11100101010101010001110 H
b100001 %
b1011101 ,
1(
#1860000
b1011110 R
0(
#1870000
b100000 %
b1011110 ,
b11101111111111111100010 :
b11101000111000110101010 ;
b11101010101010100111000 !
b11101010101010100111000 5
b11101010101010100111000 H
b1011110 S
1(
#1880000
b1011111 R
0(
#1890000
b1011111 S
b11110101010101010001100 :
b11101110001110001010100 ;
b11101111111111111100010 !
b11101111111111111100010 5
b11101111111111111100010 H
b1011111 ,
1(
#1900000
b1100000 R
0(
#1910000
b11111 %
b1100000 ,
b11111010101010100110110 :
b11110011100011011111110 ;
b11110101010101010001100 !
b11110101010101010001100 5
b11110101010101010001100 H
b1100000 S
1(
#1920000
b1100001 R
0(
#1930000
b1100001 S
b11111111111111111100000 :
b11111000111000110101000 ;
b11111010101010100110110 !
b11111010101010100110110 5
b11111010101010100110110 H
b11110 %
b1100001 ,
1(
#1940000
b1100010 R
0(
#1950000
b1100010 ,
b100000101010101010001010 :
b11111110001110001010010 ;
b11111111111111111100000 !
b11111111111111111100000 5
b11111111111111111100000 H
b1100010 S
1(
#1960000
b1100011 R
0(
#1970000
b1100011 S
b100001010101010100110100 :
b100000011100011011111100 ;
b100000101010101010001010 !
b100000101010101010001010 5
b100000101010101010001010 H
b11101 %
b1100011 ,
1(
#1980000
b1100100 R
0(
#1990000
b11100 %
b1100100 ,
b100001111111111111011110 :
b100001000111000110100110 ;
b100001010101010100110100 !
b100001010101010100110100 5
b100001010101010100110100 H
b1100100 S
1(
#2000000
b1100101 R
0(
#2010000
b1100101 S
b100010101010101010001000 :
b100001110001110001010000 ;
b100001111111111111011110 !
b100001111111111111011110 5
b100001111111111111011110 H
b1100101 ,
1(
#2020000
b1100110 R
0(
#2030000
b11011 %
b1100110 ,
b100011010101010100110010 :
b100010011100011011111010 ;
b100010101010101010001000 !
b100010101010101010001000 5
b100010101010101010001000 H
b1100110 S
1(
#2040000
b1100111 R
0(
