adsr/adsr.v
/* ===================
 * Envelope generator
 * ===================
 *
 * Creates an 8-bit ADSR (attack, decay, sustain, release) volume envelope.
 *
 *        ..
 *     A . `. D    S
 *      .    `----------
 *     .                . R
 *    .                  `  .
 *  ---------------------------->
 *                             t
 */
module adsr #(
		parameter SAMPLE_CLK_FREQ = 44100,
		parameter WIDTH = 8,
		parameter CTRL_WIDTH = 4,
		parameter ACCUMULATOR_BITS = 16

	)
	(
		clk, rst, low_clk, gate, a, d, s, r, signal_out
	);

	input wire clk, rst, low_clk;
	output wire [(ACCUMULATOR_BITS - 1):0] signal_out;

	input wire gate;
	input wire [(CTRL_WIDTH-1):0] a;
	input wire [(CTRL_WIDTH-1):0] d;
	input wire [(CTRL_WIDTH-1):0] s;
	input wire [(CTRL_WIDTH-1):0] r;

	assign signal_out = accumulator;

	localparam  ACCUMULATOR_SIZE = 2**ACCUMULATOR_BITS;
	localparam  ACCUMULATOR_MAX  = ACCUMULATOR_SIZE-1;

	reg [ACCUMULATOR_BITS-1:0] accumulator;

	localparam OFF     = 3'd0;
	localparam ATTACK  = 3'd1;
	localparam DECAY   = 3'd2;
	localparam SUSTAIN = 3'd3;
	localparam RELEASE = 3'd4;


	reg[2:0] state;

	`define CALCULATE_PHASE_INCREMENT(n) $rtoi(ACCUMULATOR_SIZE / (n * SAMPLE_CLK_FREQ))

	initial begin
		state <= OFF;
		accumulator = 0;
	end

	function [(WIDTH - 1):0] attack_table;
		input [(CTRL_WIDTH-1):0] param;
		begin
			case(param)
				4'b0000: attack_table = `CALCULATE_PHASE_INCREMENT(0.002);  // 33554
				4'b0001: attack_table = `CALCULATE_PHASE_INCREMENT(0.008);
				4'b0010: attack_table = `CALCULATE_PHASE_INCREMENT(0.016);
				4'b0011: attack_table = `CALCULATE_PHASE_INCREMENT(0.024);
				4'b0100: attack_table = `CALCULATE_PHASE_INCREMENT(0.038);
				4'b0101: attack_table = `CALCULATE_PHASE_INCREMENT(0.056);
				4'b0110: attack_table = `CALCULATE_PHASE_INCREMENT(0.068);
				4'b0111: attack_table = `CALCULATE_PHASE_INCREMENT(0.080);
				4'b1000: attack_table = `CALCULATE_PHASE_INCREMENT(0.100);
				4'b1001: attack_table = `CALCULATE_PHASE_INCREMENT(0.250);
				4'b1010: attack_table = `CALCULATE_PHASE_INCREMENT(0.500);
				4'b1011: attack_table = `CALCULATE_PHASE_INCREMENT(0.800);
				4'b1100: attack_table = `CALCULATE_PHASE_INCREMENT(1.000);
				4'b1101: attack_table = `CALCULATE_PHASE_INCREMENT(3.000);
				4'b1110: attack_table = `CALCULATE_PHASE_INCREMENT(5.000);
				4'b1111: attack_table = `CALCULATE_PHASE_INCREMENT(8.000);
				default: attack_table = 65535;
			endcase
		end
	endfunction

	function [(WIDTH - 1):0] decay_release_table;
		input [(CTRL_WIDTH-1):0] param;
		begin
			case(param)
				4'b0000: decay_release_table = `CALCULATE_PHASE_INCREMENT(0.006);
				4'b0001: decay_release_table = `CALCULATE_PHASE_INCREMENT(0.024);
				4'b0010: decay_release_table = `CALCULATE_PHASE_INCREMENT(0.048);
				4'b0011: decay_release_table = `CALCULATE_PHASE_INCREMENT(0.072);
				4'b0100: decay_release_table = `CALCULATE_PHASE_INCREMENT(0.114);
				4'b0101: decay_release_table = `CALCULATE_PHASE_INCREMENT(0.168);
				4'b0110: decay_release_table = `CALCULATE_PHASE_INCREMENT(0.204);
				4'b0111: decay_release_table = `CALCULATE_PHASE_INCREMENT(0.240);
				4'b1000: decay_release_table = `CALCULATE_PHASE_INCREMENT(0.300);
				4'b1001: decay_release_table = `CALCULATE_PHASE_INCREMENT(0.750);
				4'b1010: decay_release_table = `CALCULATE_PHASE_INCREMENT(1.500);
				4'b1011: decay_release_table = `CALCULATE_PHASE_INCREMENT(2.400);
				4'b1100: decay_release_table = `CALCULATE_PHASE_INCREMENT(3.000);
				4'b1101: decay_release_table = `CALCULATE_PHASE_INCREMENT(9.000);
				4'b1110: decay_release_table = `CALCULATE_PHASE_INCREMENT(15.00);
				4'b1111: decay_release_table = `CALCULATE_PHASE_INCREMENT(24.00);
				default: decay_release_table = 65535;
			endcase
		end
	endfunction


	// value to add to accumulator during attack phase
	// calculated from lookup table below based on attack parameter
	reg [(WIDTH - 1):0] attack_step;
	always @(a) begin
		attack_step <= attack_table(a); // convert 4-bit value into phase increment amount
	end

	// value to add to accumulator during decay phase
	// calculated from lookup table below based on decay parameter
	reg [(WIDTH - 1):0] decay_step;
	always @(d) begin
		decay_step <= decay_release_table(d); // convert 4-bit value into phase increment amount
	end

	
	reg [(WIDTH - 1):0] release_inc;
	always @(r) begin
		release_inc <= decay_release_table(r); // convert 4-bit value into phase increment amount
	end


	wire [ACCUMULATOR_BITS-1:0] next_acc_inc = accumulator + attack_step;
	wire [ACCUMULATOR_BITS-1:0] next_acc_dec = accumulator - decay_step;

	wire [ACCUMULATOR_BITS-1:0] sustain_volume;
	assign sustain_volume = s << (ACCUMULATOR_BITS - CTRL_WIDTH);

	assign overflow_max = accumulator > next_acc_inc;
	assign overflow_min = accumulator < next_acc_dec;
	assign upderflow_sust = accumulator < sustain_volume;

	always @(posedge clk) begin
		case (state)
			OFF:
				begin
					if ( gate == 1'b0 ) begin
						state <= OFF;
					end else begin
						if (overflow_max) begin
							state <= RELEASE;
						end else begin
							accumulator <= next_acc_inc;
						end
					end
				end
			ATTACK:
				begin
					if ( gate == 1'b0 ) begin
						state <= RELEASE;
					end else begin
						if (overflow_max) begin
							state <= DECAY;
						end else begin
							accumulator <= next_acc_inc;
						end
					end
				end
			DECAY:
				begin
					if ( gate == 1'b0 ) begin
						state <= RELEASE;
					end else begin
						if (upderflow_sust) begin
							state <= SUSTAIN;
						end else begin
							accumulator <= next_acc_dec;
						end
					end
				end
			SUSTAIN:
				begin
					if ( gate == 1'b0 ) begin
						state <= RELEASE;
					end
				end
			RELEASE:
				begin
					if ( gate == 1'b0 ) begin
						if (overflow_min) begin
							state <= OFF;
							accumulator <= 0;
						end else begin
							accumulator <= next_acc_dec;
						end
					end else begin
						state <= ATTACK;
					end
				end
		endcase
	end

endmodule

powerup_reset/powerup_reset.v
module powerup_reset(key, clk, rst);
	parameter TICK = 4'd15; // tick's delay 0..15
			
	input wire key;
	input wire clk;
	output reg rst;
			
	reg [3:0] tick_timer;

	initial begin
		rst <= 1;
		tick_timer <= TICK;
	end
		
	always @(posedge clk) begin
		if (key) begin
			tick_timer <= TICK;
			rst <= 1;
		end else begin
			if (tick_timer==4'd0) begin
				rst <= 0;
			end else begin
				tick_timer <= tick_timer - 1'b1;
			end
		end
	end
endmodule

common/frqdivmod.v
module frqdivmod(clk, signal_out);
parameter DIV=2;
// calculated parameters
parameter WITH = ($clog2(DIV+1)>0) ? $clog2(DIV+1) : 1;

input wire clk;
output wire signal_out;

reg clk_n; 

reg [(WITH-1):0] pos_cnt; 
reg [(WITH-1):0] neg_cnt; 

wire [(WITH-1):0] div_value = DIV[(WITH-1):0];

initial begin
	clk_n <= 1'b0;
	pos_cnt <= {(WITH){1'b0}};
	neg_cnt <= {(WITH){1'b0}};
end

assign signal_out = (DIV==1) ? clk : clk_n;

always @ (posedge clk) begin
	pos_cnt <= (pos_cnt + 1'b1) % div_value;
end

always @ (negedge clk) begin
	neg_cnt <= (neg_cnt + 1'b1) % div_value;
end

always @(clk, pos_cnt, neg_cnt) begin //pos_cnt in sens list addd for resolve warning "variable is read inside the Always Construct but isn't in the Always Construct's Event Control"
	if ((DIV%2) == 1'b0) begin
		clk_n <= ( pos_cnt >= (DIV/2)) ? 1'b1 : 1'b0;
	end else begin
		clk_n <= (( pos_cnt > (DIV/2)) || ( neg_cnt > (DIV/2))) ? 1'b1 : 1'b0;
	end
end
	
endmodule

adsr/test/testbench.v
`timescale 1us / 1ns

module testbench();
  parameter TEST_DURATION = 1000000;

  wire rst;
  wire signal_out_2;
  wire [15:0] signal_out_3;
  reg key0;
  initial key0 <= 0;

  reg clk50M;
  initial clk50M <= 0;
  always
    #10 clk50M <= ~clk50M; // Задержка 10 ns (100mhz -  50 mhz clk)

  // 50M / 44100 = 1133.78684807
  frqdivmod #(.DIV(1134)) frqdivmod_44100(
    .clk(clk50M),
    .signal_out(signal_out_2)
  );

  // генератор сброса
  powerup_reset res_gen(
    .clk(clk50M),
    .key(key0),
    .rst(rst)
  );

  reg [7:0] log_reg;
  initial log_reg <= 0;

  reg [7:0] lookup_table [0:255];
  initial begin
      $readmemh("../exp.rom", lookup_table); // Загрузка таблицы из файла
  end

  always @ (posedge clk50M) begin
    log_reg <= log_reg + 1'b1;
  end

  wire [0:255] dout;
  assign dout = lookup_table[log_reg];

	reg [3:0] a;
	reg [3:0] d;
	reg [3:0] s;
	reg [3:0] r;
	reg gate;

  initial a <= 0;
  initial d <= 0;
  initial s <= 4'b0111;
  initial r <= 0;
  initial gate <= 0;

  adsr adsr_1(
    .clk(clk50M),
    .low_clk(signal_out_2),
    .rst(rst),
    .gate(gate),
    .a(a), .d(d), .s(s), .r(r),
    .signal_out(signal_out_3)
  );

  initial
  begin
    #1000 gate <= 1;
    // #1500 gate <= 0;
    #50000 gate <= 0;
  end

  initial
  begin
    $dumpfile("out.vcd");
    $dumpvars(0,testbench);

    #TEST_DURATION;
    $display("test completed.");
    $finish;
  end
endmodule

adsr/test/out.vcd
$date
	Wed Apr 16 01:00:22 2025
$end
$version
	Icarus Verilog
$end
$timescale
	1ns
$end
$scope module testbench $end
$var wire 16 ! signal_out_3 [15:0] $end
$var wire 1 " signal_out_2 $end
$var wire 1 # rst $end
$var wire 256 $ dout [0:255] $end
$var parameter 32 % TEST_DURATION $end
$var reg 4 & a [3:0] $end
$var reg 1 ' clk50M $end
$var reg 4 ( d [3:0] $end
$var reg 1 ) gate $end
$var reg 1 * key0 $end
$var reg 8 + log_reg [7:0] $end
$var reg 4 , r [3:0] $end
$var reg 4 - s [3:0] $end
$scope module adsr_1 $end
$var wire 4 . a [3:0] $end
$var wire 1 ' clk $end
$var wire 4 / d [3:0] $end
$var wire 1 ) gate $end
$var wire 4 0 r [3:0] $end
$var wire 4 1 s [3:0] $end
$var wire 16 2 signal_out [15:0] $end
$var wire 1 3 upderflow_sust $end
$var wire 16 4 sustain_volume [15:0] $end
$var wire 1 # rst $end
$var wire 1 5 overflow_min $end
$var wire 1 6 overflow_max $end
$var wire 16 7 next_acc_inc [15:0] $end
$var wire 16 8 next_acc_dec [15:0] $end
$var wire 1 " low_clk $end
$var parameter 32 9 ACCUMULATOR_BITS $end
$var parameter 33 : ACCUMULATOR_MAX $end
$var parameter 32 ; ACCUMULATOR_SIZE $end
$var parameter 3 < ATTACK $end
$var parameter 32 = CTRL_WIDTH $end
$var parameter 3 > DECAY $end
$var parameter 3 ? OFF $end
$var parameter 3 @ RELEASE $end
$var parameter 32 A SAMPLE_CLK_FREQ $end
$var parameter 3 B SUSTAIN $end
$var parameter 32 C WIDTH $end
$var reg 16 D accumulator [15:0] $end
$var reg 8 E attack_step [7:0] $end
$var reg 8 F decay_step [7:0] $end
$var reg 8 G release_inc [7:0] $end
$var reg 3 H state [2:0] $end
$scope function attack_table $end
$var reg 4 I param [3:0] $end
$upscope $end
$scope function decay_release_table $end
$var reg 4 J param [3:0] $end
$upscope $end
$upscope $end
$scope module frqdivmod_44100 $end
$var wire 1 ' clk $end
$var wire 11 K div_value [10:0] $end
$var wire 1 " signal_out $end
$var parameter 32 L DIV $end
$var parameter 32 M WITH $end
$var reg 1 N clk_n $end
$var reg 11 O neg_cnt [10:0] $end
$var reg 11 P pos_cnt [10:0] $end
$upscope $end
$scope module res_gen $end
$var wire 1 ' clk $end
$var wire 1 * key $end
$var parameter 4 Q TICK $end
$var reg 1 # rst $end
$var reg 4 R tick_timer [3:0] $end
$upscope $end
$upscope $end
$enddefinitions $end
$comment Show the parameter values. $end
$dumpall
b1111 Q
b1011 M
b10001101110 L
b1000 C
b11 B
b1010110001000100 A
b100 @
b0 ?
b10 >
b100 =
b1 <
b10000000000000000 ;
b1111111111111111 :
b10000 9
b11110100001001000000 %
$end
#0
$dumpvars
b1111 R
b0 P
b1 O
0N
b10001101110 K
b0 J
b0 I
b0 H
b11110111 G
b11110111 F
b11100111 E
b0 D
b1111111100001001 8
b11100111 7
06
15
b111000000000000 4
13
b0 2
b111 1
b0 0
b0 /
b0 .
b111 -
b0 ,
b0 +
0*
0)
b0 (
0'
b0 &
b11111111 $
1#
0"
b0 !
$end
#10000
b1 P
b1110 R
b11111001 $
b1 +
1'
#20000
b10 O
0'
#30000
b11110100 $
b10 +
b1101 R
b10 P
1'
#40000
b11 O
0'
#50000
b11 P
b1100 R
b11101110 $
b11 +
1'
#60000
b100 O
0'
#70000
b11101001 $
b100 +
b1011 R
b100 P
1'
#80000
b101 O
0'
#90000
b101 P
b1010 R
b11100100 $
b101 +
1'
#100000
b110 O
0'
#110000
b11011111 $
b110 +
b1001 R
b110 P
1'
#120000
b111 O
0'
#130000
b111 P
b1000 R
b11011010 $
b111 +
1'
#140000
b1000 O
0'
#150000
b11010110 $
b1000 +
b111 R
b1000 P
1'
#160000
b1001 O
0'
#170000
b1001 P
b110 R
b11010001 $
b1001 +
1'
#180000
b1010 O
0'
#190000
b11001101 $
b1010 +
b101 R
b1010 P
1'
#200000
b1011 O
0'
#210000
b1011 P
b100 R
b11001000 $
b1011 +
1'
#220000
b1100 O
0'
#230000
b11000100 $
b1100 +
b11 R
b1100 P
1'
#240000
b1101 O
0'
#250000
b1101 P
b10 R
b11000000 $
b1101 +
1'
#260000
b1110 O
0'
#270000
b10111011 $
b1110 +
b1 R
b1110 P
1'
#280000
b1111 O
0'
#290000
b1111 P
b0 R
b10110111 $
b1111 +
1'
#300000
b10000 O
0'
#310000
b10110011 $
b10000 +
0#
b10000 P
1'
#320000
b10001 O
0'
#330000
b10001 P
b10110000 $
b10001 +
1'
#340000
b10010 O
0'
#350000
b10101100 $
b10010 +
b10010 P
1'
#360000
b10011 O
0'
#370000
b10011 P
b10101000 $
b10011 +
1'
#380000
b10100 O
0'
#390000
b10100100 $
b10100 +
b10100 P
1'
#400000
b10101 O
0'
#410000
b10101 P
b10100001 $
b10101 +
1'
#420000
b10110 O
0'
#430000
b10011101 $
b10110 +
b10110 P
1'
#440000
b10111 O
0'
#450000
b10111 P
b10011010 $
b10111 +
1'
#460000
b11000 O
0'
#470000
b10010111 $
b11000 +
b11000 P
1'
#480000
b11001 O
0'
#490000
b11001 P
b10010011 $
b11001 +
1'
#500000
b11010 O
0'
#510000
b10010000 $
b11010 +
b11010 P
1'
#520000
b11011 O
0'
#530000
b11011 P
b10001101 $
b11011 +
1'
#540000
b11100 O
0'
#550000
b10001010 $
b11100 +
b11100 P
1'
#560000
b11101 O
0'
#570000
b11101 P
b10000111 $
b11101 +
1'
#580000
b11110 O
0'
#590000
b10000100 $
b11110 +
b11110 P
1'
#600000
b11111 O
0'
#610000
b11111 P
b10000001 $
b11111 +
1'
#620000
b100000 O
0'
#630000
b1111110 $
b100000 +
b100000 P
1'
#640000
b100001 O
0'
#650000
b100001 P
b1111100 $
b100001 +
1'
#660000
b100010 O
0'
#670000
b1111001 $
b100010 +
b100010 P
1'
#680000
b100011 O
0'
#690000
b100011 P
b1110110 $
b100011 +
1'
#700000
b100100 O
0'
#710000
b1110100 $
b100100 +
b100100 P
1'
#720000
b100101 O
0'
#730000
b100101 P
b1110001 $
b100101 +
1'
#740000
b100110 O
0'
#750000
b1101111 $
b100110 +
b100110 P
1'
#760000
b100111 O
0'
#770000
b100111 P
b1101101 $
b100111 +
1'
#780000
b101000 O
0'
#790000
b1101010 $
b101000 +
b101000 P
1'
#800000
b101001 O
0'
#810000
b101001 P
b1101000 $
b101001 +
1'
#820000
b101010 O
0'
#830000
b1100110 $
b101010 +
b101010 P
1'
#840000
b101011 O
0'
#850000
b101011 P
b1100011 $
b101011 +
1'
#860000
b101100 O
0'
#870000
b1100001 $
b101100 +
b101100 P
1'
#880000
b101101 O
0'
#890000
b101101 P
b1011111 $
b101101 +
1'
#900000
b101110 O
0'
#910000
b1011101 $
b101110 +
b101110 P
1'
#920000
b101111 O
0'
#930000
b101111 P
b1011011 $
b101111 +
1'
#940000
b110000 O
0'
#950000
b1011001 $
b110000 +
b110000 P
1'
#960000
b110001 O
0'
#970000
b110001 P
b1010111 $
b110001 +
1'
#980000
b110010 O
0'
#990000
b1010101 $
b110010 +
b110010 P
1'
#1000000
b110011 O
0'
1)
#1010000
b110011 P
b111001110 7
b1111111111110000 8
b11100111 !
b11100111 2
b11100111 D
b1010011 $
b110011 +
1'
#1020000
b110100 O
0'
#1030000
b1010010 $
b110100 +
b1010110101 7
05
b11010111 8
b111001110 !
b111001110 2
b111001110 D
b110100 P
1'
#1040000
b110101 O
0'
#1050000
b110101 P
b1110011100 7
b110111110 8
b1010110101 !
b1010110101 2
b1010110101 D
b1010000 $
b110101 +
1'
#1060000
b110110 O
0'
#1070000
b1001110 $
b110110 +
b10010000011 7
b1010100101 8
b1110011100 !
b1110011100 2
b1110011100 D
b110110 P
1'
#1080000
b110111 O
0'
#1090000
b110111 P
b10101101010 7
b1110001100 8
b10010000011 !
b10010000011 2
b10010000011 D
b1001100 $
b110111 +
1'
#1100000
b111000 O
0'
#1110000
b1001011 $
b111000 +
b11001010001 7
b10001110011 8
b10101101010 !
b10101101010 2
b10101101010 D
b111000 P
1'
#1120000
b111001 O
0'
#1130000
b111001 P
b11100111000 7
b10101011010 8
b11001010001 !
b11001010001 2
b11001010001 D
b1001001 $
b111001 +
1'
#1140000
b111010 O
0'
#1150000
b1001000 $
b111010 +
b100000011111 7
b11001000001 8
b11100111000 !
b11100111000 2
b11100111000 D
b111010 P
1'
#1160000
b111011 O
0'
#1170000
b111011 P
b100100000110 7
b11100101000 8
b100000011111 !
b100000011111 2
b100000011111 D
b1000110 $
b111011 +
1'
#1180000
b111100 O
0'
#1190000
b1000100 $
b111100 +
b100111101101 7
b100000001111 8
b100100000110 !
b100100000110 2
b100100000110 D
b111100 P
1'
#1200000
b111101 O
0'
#1210000
b111101 P
b101011010100 7
b100011110110 8
b100111101101 !
b100111101101 2
b100111101101 D
b1000011 $
b111101 +
1'
#1220000
b111110 O
0'
#1230000
b1000010 $
b111110 +
b101110111011 7
b100111011101 8
b101011010100 !
b101011010100 2
b101011010100 D
b111110 P
1'
#1240000
b111111 O
0'
#1250000
b111111 P
b110010100010 7
b101011000100 8
b101110111011 !
b101110111011 2
b101110111011 D
b1000000 $
b111111 +
1'
#1260000
b1000000 O
0'
#1270000
b111111 $
b1000000 +
b110110001001 7
b101110101011 8
b110010100010 !
b110010100010 2
b110010100010 D
b1000000 P
1'
#1280000
b1000001 O
0'
#1290000
b1000001 P
b111001110000 7
b110010010010 8
b110110001001 !
b110110001001 2
b110110001001 D
b111101 $
b1000001 +
1'
#1300000
b1000010 O
0'
#1310000
b111100 $
b1000010 +
b111101010111 7
b110101111001 8
b111001110000 !
b111001110000 2
b111001110000 D
b1000010 P
1'
#1320000
b1000011 O
0'
#1330000
b1000011 P
b1000000111110 7
b111001100000 8
b111101010111 !
b111101010111 2
b111101010111 D
b111011 $
b1000011 +
1'
#1340000
b1000100 O
0'
#1350000
b111001 $
b1000100 +
b1000100100101 7
b111101000111 8
b1000000111110 !
b1000000111110 2
b1000000111110 D
b1000100 P
1'
#1360000
b1000101 O
0'
#1370000
b1000101 P
b1001000001100 7
b1000000101110 8
b1000100100101 !
b1000100100101 2
b1000100100101 D
b111000 $
b1000101 +
1'
#1380000
b1000110 O
0'
#1390000
b110111 $
b1000110 +
b1001011110011 7
b1000100010101 8
b1001000001100 !
b1001000001100 2
b1001000001100 D
b1000110 P
1'
#1400000
b1000111 O
0'
#1410000
b1000111 P
b1001111011010 7
b1000111111100 8
b1001011110011 !
b1001011110011 2
b1001011110011 D
b110110 $
b1000111 +
1'
#1420000
b1001000 O
0'
#1430000
b110101 $
b1001000 +
b1010011000001 7
b1001011100011 8
b1001111011010 !
b1001111011010 2
b1001111011010 D
b1001000 P
1'
#1440000
b1001001 O
0'
#1450000
b1001001 P
b1010110101000 7
b1001111001010 8
b1010011000001 !
b1010011000001 2
b1010011000001 D
b110011 $
b1001001 +
1'
#1460000
b1001010 O
0'
#1470000
b110010 $
b1001010 +
b1011010001111 7
b1010010110001 8
b1010110101000 !
b1010110101000 2
b1010110101000 D
b1001010 P
1'
#1480000
b1001011 O
0'
#1490000
b1001011 P
b1011101110110 7
b1010110011000 8
b1011010001111 !
b1011010001111 2
b1011010001111 D
b110001 $
b1001011 +
1'
#1500000
b1001100 O
0'
#1510000
b110000 $
b1001100 +
b1100001011101 7
b1011001111111 8
b1011101110110 !
b1011101110110 2
b1011101110110 D
b1001100 P
1'
#1520000
b1001101 O
0'
#1530000
b1001101 P
b1100101000100 7
b1011101100110 8
b1100001011101 !
b1100001011101 2
b1100001011101 D
b101111 $
b1001101 +
1'
#1540000
b1001110 O
0'
#1550000
b101110 $
b1001110 +
b1101000101011 7
b1100001001101 8
b1100101000100 !
b1100101000100 2
b1100101000100 D
b1001110 P
1'
#1560000
b1001111 O
0'
#1570000
b1001111 P
b1101100010010 7
b1100100110100 8
b1101000101011 !
b1101000101011 2
b1101000101011 D
b101101 $
b1001111 +
1'
#1580000
b1010000 O
0'
#1590000
b101100 $
b1010000 +
b1101111111001 7
b1101000011011 8
b1101100010010 !
b1101100010010 2
b1101100010010 D
b1010000 P
1'
#1600000
b1010001 O
0'
#1610000
b1010001 P
b1110011100000 7
b1101100000010 8
b1101111111001 !
b1101111111001 2
b1101111111001 D
b101011 $
b1010001 +
1'
#1620000
b1010010 O
0'
#1630000
b101010 $
b1010010 +
b1110111000111 7
b1101111101001 8
b1110011100000 !
b1110011100000 2
b1110011100000 D
b1010010 P
1'
#1640000
b1010011 O
0'
#1650000
b1010011 P
b1111010101110 7
b1110011010000 8
b1110111000111 !
b1110111000111 2
b1110111000111 D
b101001 $
b1010011 +
1'
#1660000
b1010100 O
0'
#1670000
b101000 $
b1010100 +
b1111110010101 7
b1110110110111 8
b1111010101110 !
b1111010101110 2
b1111010101110 D
b1010100 P
1'
#1680000
b1010101 O
0'
#1690000
b1010101 P
b10000001111100 7
b1111010011110 8
b1111110010101 !
b1111110010101 2
b1111110010101 D
b1010101 +
1'
#1700000
b1010110 O
0'
#1710000
b100111 $
b1010110 +
b10000101100011 7
b1111110000101 8
b10000001111100 !
b10000001111100 2
b10000001111100 D
b1010110 P
1'
#1720000
b1010111 O
0'
#1730000
b1010111 P
b10001001001010 7
b10000001101100 8
b10000101100011 !
b10000101100011 2
b10000101100011 D
b100110 $
b1010111 +
1'
#1740000
b1011000 O
0'
#1750000
b100101 $
b1011000 +
b10001100110001 7
b10000101010011 8
b10001001001010 !
b10001001001010 2
b10001001001010 D
b1011000 P
1'
#1760000
b1011001 O
0'
#1770000
b1011001 P
b10010000011000 7
b10001000111010 8
b10001100110001 !
b10001100110001 2
b10001100110001 D
b100100 $
b1011001 +
1'
#1780000
b1011010 O
0'
#1790000
b100011 $
b1011010 +
b10010011111111 7
b10001100100001 8
b10010000011000 !
b10010000011000 2
b10010000011000 D
b1011010 P
1'
#1800000
b1011011 O
0'
#1810000
b1011011 P
b10010111100110 7
b10010000001000 8
b10010011111111 !
b10010011111111 2
b10010011111111 D
b1011011 +
1'
#1820000
b1011100 O
0'
#1830000
b100010 $
b1011100 +
b10011011001101 7
b10010011101111 8
b10010111100110 !
b10010111100110 2
b10010111100110 D
b1011100 P
1'
#1840000
b1011101 O
0'
#1850000
b1011101 P
b10011110110100 7
b10010111010110 8
b10011011001101 !
b10011011001101 2
b10011011001101 D
b100001 $
b1011101 +
1'
#1860000
b1011110 O
0'
#1870000
b100000 $
b1011110 +
b10100010011011 7
b10011010111101 8
b10011110110100 !
b10011110110100 2
b10011110110100 D
b1011110 P
1'
#1880000
b1011111 O
0'
#1890000
b1011111 P
b10100110000010 7
b10011110100100 8
b10100010011011 !
b10100010011011 2
b10100010011011 D
b1011111 +
1'
#1900000
b1100000 O
0'
#1910000
b11111 $
b1100000 +
b10101001101001 7
b10100010001011 8
b10100110000010 !
b10100110000010 2
b10100110000010 D
b1100000 P
1'
#1920000
b1100001 O
0'
#1930000
b1100001 P
b10101101010000 7
b10100101110010 8
b10101001101001 !
b10101001101001 2
b10101001101001 D
b11110 $
b1100001 +
1'
#1940000
b1100010 O
0'
#1950000
b1100010 +
b10110000110111 7
b10101001011001 8
b10101101010000 !
b10101101010000 2
b10101101010000 D
b1100010 P
1'
#1960000
b1100011 O
0'
#1970000
b1100011 P
b10110100011110 7
b10101101000000 8
b10110000110111 !
b10110000110111 2
b10110000110111 D
b11101 $
b1100011 +
1'
#1980000
b1100100 O
0'
#1990000
b11100 $
b1100100 +
b10111000000101 7
b10110000100111 8
b10110100011110 !
b10110100011110 2
b10110100011110 D
b1100100 P
1'
#2000000
b1100101 O
0'
#2010000
b1100101 P
b10111011101100 7
b10110100001110 8
b10111000000101 !
b10111000000101 2
b10111000000101 D
b1100101 +
1'
#2020000
b1100110 O
0'
#2030000
b11011 $
b1100110 +
b10111111010011 7
b10110111110101 8
b10111011101100 !
b10111011101100 2
b10111011101100 D
b1100110 P
1'
#2040000
b1100111 O
0'
#2050000
b1100111 P
b11000010111010 7
b10111011011100 8
b10111111010011 !
b10111111010011 2
b10111111010011 D
b1100111 +
1'
#2060000
b1101000 O
0'
#2070000
b11010 $
b1101000 +
b11000110100001 7
b10111111000011 8
b11000010111010 !
b11000010111010 2
b11000010111010 D
b1101000 P
1'
#2080000
b1101001 O
0'
#2090000
b1101001 P
b11001010001000 7
b11000010101010 8
b11000110100001 !
b11000110100001 2
b11000110100001 D
b11001 $
b1101001 +
1'
#2100000
b1101010 O
0'
#2110000
b1101010 +
b11001101101111 7
b11000110010001 8
b11001010001000 !
b11001010001000 2
b11001010001000 D
b1101010 P
1'
#2120000
b1101011 O
0'
#2130000
b1101011 P
b11010001010110 7
b11001001111000 8
b11001101101111 !
b11001101101111 2
b11001101101111 D
b11000 $
b1101011 +
1'
#2140000
b1101100 O
0'
#2150000
b1101100 +
b11010100111101 7
b11001101011111 8
b11010001010110 !
b11010001010110 2
b11010001010110 D
b1101100 P
1'
#2160000
b1101101 O
0'
#2170000
b1101101 P
b11011000100100 7
b11010001000110 8
b11010100111101 !
b11010100111101 2
b11010100111101 D
b10111 $
b1101101 +
1'
#2180000
b1101110 O
0'
#2190000
b1101110 +
b11011100001011 7
b11010100101101 8
b11011000100100 !
b11011000100100 2
b11011000100100 D
b1101110 P
1'
#2200000
b1101111 O
0'
#2210000
b1101111 P
b11011111110010 7
b11011000010100 8
b11011100001011 !
b11011100001011 2
b11011100001011 D
b10110 $
b1101111 +
1'
#2220000
b1110000 O
0'
#2230000
b1110000 +
b11100011011001 7
b11011011111011 8
b11011111110010 !
b11011111110010 2
b11011111110010 D
b1110000 P
1'
#2240000
b1110001 O
0'
#2250000
b1110001 P
b11100111000000 7
b11011111100010 8
b11100011011001 !
b11100011011001 2
b11100011011001 D
b10101 $
b1110001 +
1'
#2260000
b1110010 O
0'
#2270000
b1110010 +
b11101010100111 7
b11100011001001 8
b11100111000000 !
b11100111000000 2
b11100111000000 D
b1110010 P
1'
#2280000
b1110011 O
0'
#2290000
b1110011 P
b11101110001110 7
b11100110110000 8
b11101010100111 !
b11101010100111 2
b11101010100111 D
b10100 $
b1110011 +
1'
#2300000
b1110100 O
0'
#2310000
b1110100 +
b11110001110101 7
b11101010010111 8
b11101110001110 !
b11101110001110 2
b11101110001110 D
b1110100 P
1'
#2320000
b1110101 O
0'
#2330000
b1110101 P
b11110101011100 7
b11101101111110 8
b11110001110101 !
b11110001110101 2
b11110001110101 D
b10011 $
b1110101 +
1'
#2340000
b1110110 O
0'
#2350000
b1110110 +
b11111001000011 7
b11110001100101 8
b11110101011100 !
b11110101011100 2
b11110101011100 D
b1110110 P
1'
#2360000
b1110111 O
0'
#2370000
b1110111 P
b11111100101010 7
b11110101001100 8
b11111001000011 !
b11111001000011 2
b11111001000011 D
b1110111 +
1'
#2380000
b1111000 O
0'
#2390000
b10010 $
b1111000 +
b100000000010001 7
b11111000110011 8
b11111100101010 !
b11111100101010 2
b11111100101010 D
b1111000 P
1'
#2400000
b1111001 O
0'
#2410000
b1111001 P
b100000011111000 7
b11111100011010 8
b100000000010001 !
b100000000010001 2
b100000000010001 D
b1111001 +
1'
#2420000
b1111010 O
0'
#2430000
b10001 $
b1111010 +
b100000111011111 7
b100000000000001 8
b100000011111000 !
b100000011111000 2
b100000011111000 D
b1111010 P
1'
#2440000
b1111011 O
0'
#2450000
b1111011 P
b100001011000110 7
b100000011101000 8
b100000111011111 !
b100000111011111 2
b100000111011111 D
b1111011 +
1'
#2460000
b1111100 O
0'
#2470000
b1111100 +
b100001110101101 7
b100000111001111 8
b100001011000110 !
b100001011000110 2
b100001011000110 D
b1111100 P
1'
#2480000
b1111101 O
0'
#2490000
b1111101 P
b100010010010100 7
b100001010110110 8
b100001110101101 !
b100001110101101 2
b100001110101101 D
b10000 $
b1111101 +
1'
#2500000
b1111110 O
0'
#2510000
b1111110 +
b100010101111011 7
b100001110011101 8
b100010010010100 !
b100010010010100 2
b100010010010100 D
b1111110 P
1'
#2520000
b1111111 O
0'
#2530000
b1111111 P
b100011001100010 7
b100010010000100 8
b100010101111011 !
b100010101111011 2
b100010101111011 D
b1111111 +
1'
#2540000
b10000000 O
0'
#2550000
b1111 $
b10000000 +
b100011101001001 7
b100010101101011 8
b100011001100010 !
b100011001100010 2
b100011001100010 D
b10000000 P
1'
#2560000
b10000001 O
0'
#2570000
b10000001 P
b100100000110000 7
b100011001010010 8
b100011101001001 !
b100011101001001 2
b100011101001001 D
b10000001 +
1'
