common/strobe_gen.v
module strobe_gen(clk, f, signal_out);
		
	input wire f;
	input wire clk;
	output wire signal_out;
			
	reg prev;

	initial begin
		prev <= 1'b0;
	end
		
	always @(posedge clk) begin
		prev <= f;
	end

    assign signal_out = ((f==1'b1)&&(prev==1'b0));
endmodule

common/frqdivmod.v
module frqdivmod(clk, signal_out);
parameter DIV=2;
// calculated parameters
parameter WITH = ($clog2(DIV+1)>0) ? $clog2(DIV+1) : 1;

input wire clk;
output wire signal_out;

reg clk_n; 

reg [(WITH-1):0] pos_cnt; 
reg [(WITH-1):0] neg_cnt; 

wire [(WITH-1):0] div_value = DIV[(WITH-1):0];

initial begin
	clk_n <= 1'b0;
	pos_cnt <= {(WITH){1'b0}};
	neg_cnt <= {(WITH){1'b0}};
end

assign signal_out = (DIV==1) ? clk : clk_n;

always @ (posedge clk) begin
	pos_cnt <= (pos_cnt + 1'b1) % div_value;
end

always @ (negedge clk) begin
	neg_cnt <= (neg_cnt + 1'b1) % div_value;
end

always @(clk, pos_cnt, neg_cnt) begin //pos_cnt in sens list addd for resolve warning "variable is read inside the Always Construct but isn't in the Always Construct's Event Control"
	if ((DIV%2) == 1'b0) begin
		clk_n <= ( pos_cnt >= (DIV/2)) ? 1'b1 : 1'b0;
	end else begin
		clk_n <= (( pos_cnt > (DIV/2)) || ( neg_cnt > (DIV/2))) ? 1'b1 : 1'b0;
	end
end
	
endmodule

common/strobe_gen_test/testbench.v
`timescale 1us / 1ns

module testbench();
  parameter TEST_DURATION = 1000000;

  wire rst;
  wire signal_out_2;
  wire signal_out_3;
  wire signal_out_4;

  wire signal_out_2_up;
  wire signal_out_3_up;
  wire signal_out_4_up;

  reg clk50M;
  initial clk50M <= 0;
  always
    #10 clk50M <= ~clk50M; // Задержка 10 ns (100mhz -  50 mhz clk)

  frqdivmod #(.DIV(20)) frqdivmod_2(
    .clk(clk50M),
    .signal_out(signal_out_2)
  );

  frqdivmod #(.DIV(30)) frqdivmod_3(
    .clk(clk50M),
    .signal_out(signal_out_3)
  );

  frqdivmod #(.DIV(40)) frqdivmod_4(
    .clk(clk50M),
    .signal_out(signal_out_4)
  );

  strobe_gen strobe_gen_1(
    .clk(clk50M),
    .f(signal_out_2),
    .signal_out(signal_out_2_up)
  );

  strobe_gen strobe_gen_2(
    .clk(clk50M),
    .f(signal_out_3),
    .signal_out(signal_out_3_up)
  );

  strobe_gen strobe_gen_3(
    .clk(clk50M),
    .f(signal_out_4),
    .signal_out(signal_out_4_up)
  );

  initial
  begin
    $dumpfile("out.vcd");
    $dumpvars(0,testbench);

    #TEST_DURATION;
    $display("test completed.");
    $finish;
  end
endmodule

common/strobe_gen_test/out.vcd
$date
	Thu Nov  7 01:01:28 2024
$end
$version
	Icarus Verilog
$end
$timescale
	1ns
$end
$scope module testbench $end
$var wire 1 ! signal_out_4_up $end
$var wire 1 " signal_out_4 $end
$var wire 1 # signal_out_3_up $end
$var wire 1 $ signal_out_3 $end
$var wire 1 % signal_out_2_up $end
$var wire 1 & signal_out_2 $end
$var parameter 32 ' TEST_DURATION $end
$var reg 1 ( clk50M $end
$scope module frqdivmod_2 $end
$var wire 1 ( clk $end
$var wire 5 ) div_value [4:0] $end
$var wire 1 & signal_out $end
$var parameter 32 * DIV $end
$var parameter 32 + WITH $end
$var reg 1 & clk_n $end
$var reg 5 , neg_cnt [4:0] $end
$var reg 5 - pos_cnt [4:0] $end
$upscope $end
$scope module frqdivmod_3 $end
$var wire 1 ( clk $end
$var wire 5 . div_value [4:0] $end
$var wire 1 $ signal_out $end
$var parameter 32 / DIV $end
$var parameter 32 0 WITH $end
$var reg 1 $ clk_n $end
$var reg 5 1 neg_cnt [4:0] $end
$var reg 5 2 pos_cnt [4:0] $end
$upscope $end
$scope module frqdivmod_4 $end
$var wire 1 ( clk $end
$var wire 6 3 div_value [5:0] $end
$var wire 1 " signal_out $end
$var parameter 32 4 DIV $end
$var parameter 32 5 WITH $end
$var reg 1 " clk_n $end
$var reg 6 6 neg_cnt [5:0] $end
$var reg 6 7 pos_cnt [5:0] $end
$upscope $end
$scope module strobe_gen_1 $end
$var wire 1 ( clk $end
$var wire 1 & f $end
$var wire 1 % signal_out $end
$var reg 1 8 prev $end
$upscope $end
$scope module strobe_gen_2 $end
$var wire 1 ( clk $end
$var wire 1 $ f $end
$var wire 1 # signal_out $end
$var reg 1 9 prev $end
$upscope $end
$scope module strobe_gen_3 $end
$var wire 1 ( clk $end
$var wire 1 " f $end
$var wire 1 ! signal_out $end
$var reg 1 : prev $end
$upscope $end
$upscope $end
$enddefinitions $end
$comment Show the parameter values. $end
$dumpall
b110 5
b101000 4
b101 0
b11110 /
b101 +
b10100 *
b11110100001001000000 '
$end
#0
$dumpvars
0:
09
08
b0 7
b1 6
b101000 3
b0 2
b1 1
b11110 .
b0 -
b1 ,
b10100 )
0(
0&
0%
0$
0#
0"
0!
$end
#10000
b1 -
b1 2
b1 7
1(
#20000
b10 6
b10 1
b10 ,
0(
#30000
b10 7
b10 2
b10 -
1(
#40000
b11 ,
b11 1
b11 6
0(
#50000
b11 -
b11 2
b11 7
1(
#60000
b100 6
b100 1
b100 ,
0(
#70000
b100 7
b100 2
b100 -
1(
#80000
b101 ,
b101 1
b101 6
0(
#90000
b101 -
b101 2
b101 7
1(
#100000
b110 6
b110 1
b110 ,
0(
#110000
b110 7
b110 2
b110 -
1(
#120000
b111 ,
b111 1
b111 6
0(
#130000
b111 -
b111 2
b111 7
1(
#140000
b1000 6
b1000 1
b1000 ,
0(
#150000
b1000 7
b1000 2
b1000 -
1(
#160000
b1001 ,
b1001 1
b1001 6
0(
#170000
b1001 -
b1001 2
b1001 7
1(
#180000
b1010 6
b1010 1
b1010 ,
0(
#190000
1%
1&
b1010 7
b1010 2
b1010 -
1(
#200000
b1011 ,
b1011 1
b1011 6
0(
#210000
0%
b1011 -
b1011 2
b1011 7
18
1(
#220000
b1100 6
b1100 1
b1100 ,
0(
#230000
b1100 7
b1100 2
b1100 -
1(
#240000
b1101 ,
b1101 1
b1101 6
0(
#250000
b1101 -
b1101 2
b1101 7
1(
#260000
b1110 6
b1110 1
b1110 ,
0(
#270000
b1110 7
b1110 2
b1110 -
1(
#280000
b1111 ,
b1111 1
b1111 6
0(
#290000
1#
1$
b1111 -
b1111 2
b1111 7
1(
#300000
b10000 6
b10000 1
b10000 ,
0(
#310000
0#
19
b10000 7
b10000 2
b10000 -
1(
#320000
b10001 ,
b10001 1
b10001 6
0(
#330000
b10001 -
b10001 2
b10001 7
1(
#340000
b10010 6
b10010 1
b10010 ,
0(
#350000
b10010 7
b10010 2
b10010 -
1(
#360000
b10011 ,
b10011 1
b10011 6
0(
#370000
b10011 -
b10011 2
b10011 7
1(
#380000
b10100 6
b10100 1
b0 ,
0(
#390000
1!
1"
0&
b10100 7
b10100 2
b0 -
1(
#400000
b1 ,
b10101 1
b10101 6
0(
#410000
0!
b1 -
b10101 2
b10101 7
08
1:
1(
#420000
b10110 6
b10110 1
b10 ,
0(
#430000
b10110 7
b10110 2
b10 -
1(
#440000
b11 ,
b10111 1
b10111 6
0(
#450000
b11 -
b10111 2
b10111 7
1(
#460000
b11000 6
b11000 1
b100 ,
0(
#470000
b11000 7
b11000 2
b100 -
1(
#480000
b101 ,
b11001 1
b11001 6
0(
#490000
b101 -
b11001 2
b11001 7
1(
#500000
b11010 6
b11010 1
b110 ,
0(
#510000
b11010 7
b11010 2
b110 -
1(
#520000
b111 ,
b11011 1
b11011 6
0(
#530000
b111 -
b11011 2
b11011 7
1(
#540000
b11100 6
b11100 1
b1000 ,
0(
#550000
b11100 7
b11100 2
b1000 -
1(
#560000
b1001 ,
b11101 1
b11101 6
0(
#570000
b1001 -
b11101 2
b11101 7
1(
#580000
b11110 6
b0 1
b1010 ,
0(
#590000
1%
0$
1&
b11110 7
b0 2
b1010 -
1(
#600000
b1011 ,
b1 1
b11111 6
0(
#610000
0%
b1011 -
b1 2
b11111 7
18
09
1(
#620000
b100000 6
b10 1
b1100 ,
0(
#630000
b100000 7
b10 2
b1100 -
1(
#640000
b1101 ,
b11 1
b100001 6
0(
#650000
b1101 -
b11 2
b100001 7
1(
#660000
b100010 6
b100 1
b1110 ,
0(
#670000
b100010 7
b100 2
b1110 -
1(
#680000
b1111 ,
b101 1
b100011 6
0(
#690000
b1111 -
b101 2
b100011 7
1(
#700000
b100100 6
b110 1
b10000 ,
0(
#710000
b100100 7
b110 2
b10000 -
1(
#720000
b10001 ,
b111 1
b100101 6
0(
#730000
b10001 -
b111 2
b100101 7
1(
#740000
b100110 6
b1000 1
b10010 ,
0(
#750000
b100110 7
b1000 2
b10010 -
1(
#760000
b10011 ,
b1001 1
b100111 6
0(
#770000
b10011 -
b1001 2
b100111 7
1(
#780000
b0 6
b1010 1
b0 ,
0(
#790000
0"
0&
b0 7
b1010 2
b0 -
1(
#800000
b1 ,
b1011 1
b1 6
0(
#810000
b1 -
b1011 2
b1 7
08
0:
1(
#820000
b10 6
b1100 1
b10 ,
0(
#830000
b10 7
b1100 2
b10 -
1(
#840000
b11 ,
b1101 1
b11 6
0(
#850000
b11 -
b1101 2
b11 7
1(
#860000
b100 6
b1110 1
b100 ,
0(
#870000
b100 7
b1110 2
b100 -
1(
#880000
b101 ,
b1111 1
b101 6
0(
#890000
1#
1$
b101 -
b1111 2
b101 7
1(
#900000
b110 6
b10000 1
b110 ,
0(
#910000
0#
19
b110 7
b10000 2
b110 -
1(
#920000
b111 ,
b10001 1
b111 6
0(
#930000
b111 -
b10001 2
b111 7
1(
#940000
b1000 6
b10010 1
b1000 ,
0(
#950000
b1000 7
b10010 2
b1000 -
1(
#960000
b1001 ,
b10011 1
b1001 6
0(
#970000
b1001 -
b10011 2
b1001 7
1(
#980000
b1010 6
b10100 1
b1010 ,
0(
#990000
1%
1&
b1010 7
b10100 2
b1010 -
1(
#1000000
b1011 ,
b10101 1
b1011 6
0(
#1010000
0%
b1011 -
b10101 2
b1011 7
18
1(
#1020000
b1100 6
b10110 1
b1100 ,
0(
#1030000
b1100 7
b10110 2
b1100 -
1(
#1040000
b1101 ,
b10111 1
b1101 6
0(
#1050000
b1101 -
b10111 2
b1101 7
1(
#1060000
b1110 6
b11000 1
b1110 ,
0(
#1070000
b1110 7
b11000 2
b1110 -
1(
#1080000
b1111 ,
b11001 1
b1111 6
0(
#1090000
b1111 -
b11001 2
b1111 7
1(
#1100000
b10000 6
b11010 1
b10000 ,
0(
#1110000
b10000 7
b11010 2
b10000 -
1(
#1120000
b10001 ,
b11011 1
b10001 6
0(
#1130000
b10001 -
b11011 2
b10001 7
1(
#1140000
b10010 6
b11100 1
b10010 ,
0(
#1150000
b10010 7
b11100 2
b10010 -
1(
#1160000
b10011 ,
b11101 1
b10011 6
0(
#1170000
b10011 -
b11101 2
b10011 7
1(
#1180000
b10100 6
b0 1
b0 ,
0(
#1190000
1!
1"
0$
0&
b10100 7
b0 2
b0 -
1(
#1200000
b1 ,
b1 1
b10101 6
0(
#1210000
0!
b1 -
b1 2
b10101 7
08
09
1:
1(
#1220000
b10110 6
b10 1
b10 ,
0(
#1230000
b10110 7
b10 2
b10 -
1(
#1240000
b11 ,
b11 1
b10111 6
0(
#1250000
b11 -
b11 2
b10111 7
1(
#1260000
b11000 6
b100 1
b100 ,
0(
#1270000
b11000 7
b100 2
b100 -
1(
#1280000
b101 ,
b101 1
b11001 6
0(
#1290000
b101 -
b101 2
b11001 7
1(
#1300000
b11010 6
b110 1
b110 ,
0(
#1310000
b11010 7
b110 2
b110 -
1(
#1320000
b111 ,
b111 1
b11011 6
0(
#1330000
b111 -
b111 2
b11011 7
1(
#1340000
b11100 6
b1000 1
b1000 ,
0(
#1350000
b11100 7
b1000 2
b1000 -
1(
#1360000
b1001 ,
b1001 1
b11101 6
0(
#1370000
b1001 -
b1001 2
b11101 7
1(
#1380000
b11110 6
b1010 1
b1010 ,
0(
#1390000
1%
1&
b11110 7
b1010 2
b1010 -
1(
#1400000
b1011 ,
b1011 1
b11111 6
0(
#1410000
0%
b1011 -
b1011 2
b11111 7
18
1(
#1420000
b100000 6
b1100 1
b1100 ,
0(
#1430000
b100000 7
b1100 2
b1100 -
1(
#1440000
b1101 ,
b1101 1
b100001 6
0(
#1450000
b1101 -
b1101 2
b100001 7
1(
#1460000
b100010 6
b1110 1
b1110 ,
0(
#1470000
b100010 7
b1110 2
b1110 -
1(
#1480000
b1111 ,
b1111 1
b100011 6
0(
#1490000
1#
1$
b1111 -
b1111 2
b100011 7
1(
#1500000
b100100 6
b10000 1
b10000 ,
0(
#1510000
0#
19
b100100 7
b10000 2
b10000 -
1(
#1520000
b10001 ,
b10001 1
b100101 6
0(
#1530000
b10001 -
b10001 2
b100101 7
1(
#1540000
b100110 6
b10010 1
b10010 ,
0(
#1550000
b100110 7
b10010 2
b10010 -
1(
#1560000
b10011 ,
b10011 1
b100111 6
0(
#1570000
b10011 -
b10011 2
b100111 7
1(
#1580000
b0 6
b10100 1
b0 ,
0(
#1590000
0"
0&
b0 7
b10100 2
b0 -
1(
#1600000
b1 ,
b10101 1
b1 6
0(
#1610000
b1 -
b10101 2
b1 7
08
0:
1(
#1620000
b10 6
b10110 1
b10 ,
0(
#1630000
b10 7
b10110 2
b10 -
1(
#1640000
b11 ,
b10111 1
b11 6
0(
#1650000
b11 -
b10111 2
b11 7
1(
#1660000
b100 6
b11000 1
b100 ,
0(
#1670000
b100 7
b11000 2
b100 -
1(
#1680000
b101 ,
b11001 1
b101 6
0(
#1690000
b101 -
b11001 2
b101 7
1(
#1700000
b110 6
b11010 1
b110 ,
0(
#1710000
b110 7
b11010 2
b110 -
1(
#1720000
b111 ,
b11011 1
b111 6
0(
#1730000
b111 -
b11011 2
b111 7
1(
#1740000
b1000 6
b11100 1
b1000 ,
0(
#1750000
b1000 7
b11100 2
b1000 -
1(
#1760000
b1001 ,
b11101 1
b1001 6
0(
#1770000
b1001 -
b11101 2
b1001 7
1(
#1780000
b1010 6
b0 1
b1010 ,
0(
#1790000
1%
0$
1&
b1010 7
b0 2
b1010 -
1(
#1800000
b1011 ,
b1 1
b1011 6
0(
#1810000
0%
b1011 -
b1 2
b1011 7
18
09
1(
#1820000
b1100 6
b10 1
b1100 ,
0(
#1830000
b1100 7
b10 2
b1100 -
1(
#1840000
b1101 ,
b11 1
b1101 6
0(
#1850000
b1101 -
b11 2
b1101 7
1(
#1860000
b1110 6
b100 1
b1110 ,
0(
#1870000
b1110 7
b100 2
b1110 -
1(
#1880000
b1111 ,
b101 1
b1111 6
0(
#1890000
b1111 -
b101 2
b1111 7
1(
#1900000
b10000 6
b110 1
b10000 ,
0(
#1910000
b10000 7
b110 2
b10000 -
1(
#1920000
b10001 ,
b111 1
b10001 6
0(
#1930000
b10001 -
b111 2
b10001 7
1(
#1940000
b10010 6
b1000 1
b10010 ,
0(
#1950000
b10010 7
b1000 2
b10010 -
1(
#1960000
b10011 ,
b1001 1
b10011 6
0(
#1970000
b10011 -
b1001 2
b10011 7
1(
#1980000
b10100 6
b1010 1
b0 ,
0(
#1990000
1!
1"
0&
b10100 7
b1010 2
b0 -
1(
#2000000
b1 ,
b1011 1
b10101 6
0(
#2010000
0!
b1 -
b1011 2
b10101 7
08
1:
1(
#2020000
b10110 6
b1100 1
b10 ,
0(
#2030000
b10110 7
b1100 2
b10 -
1(
#2040000
b11 ,
b1101 1
b10111 6
0(
#2050000
b11 -
b1101 2
b10111 7
1(
#2060000
b11000 6
b1110 1
b100 ,
0(
#2070000
b11000 7
b1110 2
b100 -
1(
#2080000
b101 ,
b1111 1
b11001 6
0(
#2090000
1#
1$
b101 -
b1111 2
b11001 7
1(
#2100000
b11010 6
b10000 1
b110 ,
0(
#2110000
0#
19
b11010 7
b10000 2
b110 -
1(
#2120000
b111 ,
b10001 1
b11011 6
0(
#2130000
b111 -
b10001 2
b11011 7
1(
#2140000
b11100 6
b10010 1
b1000 ,
0(
#2150000
b11100 7
b10010 2
b1000 -
1(
#2160000
b1001 ,
b10011 1
b11101 6
0(
#2170000
b1001 -
b10011 2
b11101 7
1(
#2180000
b11110 6
b10100 1
b1010 ,
0(
#2190000
1%
1&
b11110 7
b10100 2
b1010 -
1(
#2200000
b1011 ,
b10101 1
b11111 6
0(
#2210000
0%
b1011 -
b10101 2
b11111 7
18
1(
#2220000
b100000 6
b10110 1
b1100 ,
0(
#2230000
b100000 7
b10110 2
b1100 -
1(
#2240000
b1101 ,
b10111 1
b100001 6
0(
#2250000
b1101 -
b10111 2
b100001 7
1(
#2260000
b100010 6
b11000 1
b1110 ,
0(
#2270000
b100010 7
b11000 2
b1110 -
1(
#2280000
b1111 ,
b11001 1
b100011 6
0(
#2290000
b1111 -
b11001 2
b100011 7
1(
#2300000
b100100 6
b11010 1
b10000 ,
0(
#2310000
b100100 7
b11010 2
b10000 -
1(
#2320000
b10001 ,
b11011 1
b100101 6
0(
#2330000
b10001 -
b11011 2
b100101 7
1(
#2340000
b100110 6
b11100 1
b10010 ,
0(
#2350000
b100110 7
b11100 2
b10010 -
1(
#2360000
b10011 ,
b11101 1
b100111 6
0(
#2370000
b10011 -
b11101 2
b100111 7
1(
#2380000
b0 6
b0 1
b0 ,
0(
#2390000
0"
0$
0&
b0 7
b0 2
b0 -
1(
#2400000
b1 ,
b1 1
b1 6
0(
#2410000
b1 -
b1 2
b1 7
08
09
0:
1(
#2420000
b10 6
b10 1
b10 ,
0(
#2430000
b10 7
b10 2
b10 -
1(
#2440000
b11 ,
b11 1
b11 6
0(
#2450000
b11 -
b11 2
b11 7
1(
#2460000
b100 6
b100 1
b100 ,
0(
#2470000
b100 7
b100 2
b100 -
1(
#2480000
b101 ,
b101 1
b101 6
0(
#2490000
b101 -
b101 2
b101 7
1(
#2500000
b110 6
b110 1
b110 ,
0(
#2510000
b110 7
b110 2
b110 -
1(
#2520000
b111 ,
b111 1
b111 6
0(
#2530000
b111 -
b111 2
b111 7
1(
#2540000
b1000 6
b1000 1
b1000 ,
0(
#2550000
b1000 7
b1000 2
b1000 -
1(
#2560000
b1001 ,
b1001 1
b1001 6
0(
#2570000
b1001 -
b1001 2
b1001 7
1(
#2580000
b1010 6
b1010 1
b1010 ,
0(
#2590000
1%
1&
b1010 7
b1010 2
b1010 -
1(
#2600000
b1011 ,
b1011 1
b1011 6
0(
#2610000
0%
b1011 -
b1011 2
b1011 7
18
1(
#2620000
b1100 6
b1100 1
b1100 ,
0(
#2630000
b1100 7
b1100 2
b1100 -
1(
#2640000
b1101 ,
b1101 1
b1101 6
0(
#2650000
b1101 -
b1101 2
b1101 7
1(
#2660000
b1110 6
b1110 1
b1110 ,
0(
#2670000
b1110 7
b1110 2
b1110 -
1(
#2680000
b1111 ,
b1111 1
b1111 6
0(
#2690000
1#
1$
b1111 -
b1111 2
b1111 7
1(
#2700000
b10000 6
b10000 1
b10000 ,
0(
#2710000
0#
19
b10000 7
b10000 2
b10000 -
1(
#2720000
b10001 ,
b10001 1
b10001 6
0(
#2730000
b10001 -
b10001 2
b10001 7
1(
#2740000
b10010 6
b10010 1
b10010 ,
0(
#2750000
b10010 7
b10010 2
b10010 -
1(
#2760000
b10011 ,
b10011 1
b10011 6
0(
#2770000
b10011 -
b10011 2
b10011 7
1(
#2780000
b10100 6
b10100 1
b0 ,
0(
#2790000
1!
1"
0&
b10100 7
b10100 2
b0 -
1(
#2800000
b1 ,
b10101 1
b10101 6
0(
#2810000
0!
b1 -
b10101 2
b10101 7
08
1:
1(
#2820000
b10110 6
b10110 1
b10 ,
0(
#2830000
b10110 7
b10110 2
b10 -
1(
#2840000
b11 ,
b10111 1
b10111 6
0(
#2850000
b11 -
b10111 2
b10111 7
1(
#2860000
b11000 6
b11000 1
b100 ,
0(
#2870000
b11000 7
b11000 2
b100 -
1(
#2880000
b101 ,
b11001 1
b11001 6
0(
#2890000
b101 -
b11001 2
b11001 7
1(
#2900000
b11010 6
b11010 1
b110 ,
0(
#2910000
b11010 7
b11010 2
b110 -
1(
#2920000
b111 ,
b11011 1
b11011 6
0(
#2930000
b111 -
b11011 2
b11011 7
1(
#2940000
b11100 6
b11100 1
b1000 ,
0(
#2950000
b11100 7
b11100 2
b1000 -
1(
#2960000
b1001 ,
b11101 1
b11101 6
0(
#2970000
b1001 -
b11101 2
b11101 7
1(
#2980000
b11110 6
b0 1
b1010 ,
0(
#2990000
1%
0$
1&
b11110 7
b0 2
b1010 -
1(
#3000000
b1011 ,
b1 1
b11111 6
0(
#3010000
0%
b1011 -
b1 2
b11111 7
18
09
1(
#3020000
b100000 6
b10 1
b1100 ,
0(
#3030000
b100000 7
b10 2
b1100 -
1(
#3040000
b1101 ,
b11 1
b100001 6
0(
#3050000
b1101 -
b11 2
b100001 7
1(
#3060000
b100010 6
b100 1
b1110 ,
0(
#3070000
b100010 7
b100 2
b1110 -
1(
#3080000
b1111 ,
b101 1
b100011 6
0(
#3090000
b1111 -
b101 2
b100011 7
1(
#3100000
b100100 6
b110 1
b10000 ,
0(
#3110000
b100100 7
b110 2
b10000 -
1(
#3120000
b10001 ,
b111 1
b100101 6
0(
#3130000
b10001 -
b111 2
b100101 7
1(
#3140000
b100110 6
b1000 1
b10010 ,
0(
#3150000
b100110 7
b1000 2
b10010 -
1(
#3160000
b10011 ,
b1001 1
b100111 6
0(
#3170000
b10011 -
b1001 2
b100111 7
1(
#3180000
b0 6
b1010 1
b0 ,
0(
#3190000
0"
0&
b0 7
b1010 2
b0 -
1(
#3200000
b1 ,
b1011 1
b1 6
0(
#3210000
b1 -
b1011 2
b1 7
08
0:
1(
#3220000
b10 6
b1100 1
b10 ,
0(
#3230000
b10 7
b1100 2
b10 -
1(
#3240000
b11 ,
b1101 1
b11 6
0(
#3250000
b11 -
b1101 2
b11 7
1(
#3260000
b100 6
b1110 1
b100 ,
0(
#3270000
b100 7
b1110 2
b100 -
1(
#3280000
b101 ,
b1111 1
b101 6
0(
#3290000
1#
1$
b101 -
b1111 2
b101 7
1(
#3300000
b110 6
b10000 1
b110 ,
0(
#3310000
0#
19
b110 7
b10000 2
b110 -
1(
#3320000
b111 ,
b10001 1
b111 6
0(
#3330000
b111 -
b10001 2
b111 7
1(
#3340000
b1000 6
b10010 1
b1000 ,
0(
#3350000
b1000 7
b10010 2
b1000 -
1(
#3360000
b1001 ,
b10011 1
b1001 6
0(
#3370000
b1001 -
b10011 2
b1001 7
1(
#3380000
b1010 6
b10100 1
b1010 ,
0(
#3390000
1%
1&
b1010 7
b10100 2
b1010 -
1(
#3400000
b1011 ,
b10101 1
b1011 6
0(
#3410000
0%
b1011 -
b10101 2
b1011 7
18
1(
#3420000
b1100 6
b10110 1
b1100 ,
0(
#3430000
b1100 7
b10110 2
b1100 -
1(
#3440000
b1101 ,
b10111 1
b1101 6
0(
#3450000
b1101 -
b10111 2
b1101 7
1(
#3460000
b1110 6
b11000 1
b1110 ,
0(
#3470000
b1110 7
b11000 2
b1110 -
1(
#3480000
b1111 ,
b11001 1
b1111 6
0(
#3490000
b1111 -
b11001 2
b1111 7
1(
#3500000
b10000 6
b11010 1
b10000 ,
0(
#3510000
b10000 7
b11010 2
b10000 -
1(
#3520000
b10001 ,
b11011 1
b10001 6
0(
#3530000
b10001 -
b11011 2
b10001 7
1(
#3540000
b10010 6
b11100 1
b10010 ,
0(
#3550000
b10010 7
b11100 2
b10010 -
1(
#3560000
b10011 ,
b11101 1
b10011 6
0(
#3570000
b10011 -
b11101 2
b10011 7
1(
#3580000
b10100 6
b0 1
b0 ,
0(
#3590000
1!
1"
0$
0&
b10100 7
b0 2
b0 -
1(
#3600000
b1 ,
b1 1
b10101 6
0(
#3610000
0!
b1 -
b1 2
b10101 7
08
09
1:
1(
#3620000
b10110 6
b10 1
b10 ,
0(
#3630000
b10110 7
b10 2
b10 -
1(
#3640000
b11 ,
b11 1
b10111 6
0(
#3650000
b11 -
b11 2
b10111 7
1(
#3660000
b11000 6
b100 1
b100 ,
0(
#3670000
b11000 7
b100 2
b100 -
1(
#3680000
b101 ,
b101 1
b11001 6
0(
#3690000
b101 -
b101 2
b11001 7
1(
#3700000
b11010 6
b110 1
b110 ,
0(
#3710000
b11010 7
b110 2
b110 -
1(
#3720000
b111 ,
b111 1
b11011 6
0(
#3730000
b111 -
b111 2
b11011 7
1(
#3740000
b11100 6
b1000 1
b1000 ,
0(
#3750000
b11100 7
b1000 2
b1000 -
1(
#3760000
b1001 ,
b1001 1
b11101 6
0(
#3770000
b1001 -
b1001 2
b11101 7
1(
#3780000
b11110 6
b1010 1
b1010 ,
0(
#3790000
1%
1&
b11110 7
b1010 2
b1010 -
1(
#3800000
b1011 ,
b1011 1
b11111 6
0(
#3810000
0%
b1011 -
b1011 2
b11111 7
18
1(
#3820000
b100000 6
b1100 1
b1100 ,
0(
#3830000
b100000 7
b1100 2
b1100 -
1(
#3840000
b1101 ,
b1101 1
b100001 6
0(
#3850000
b1101 -
b1101 2
b100001 7
1(
#3860000
b100010 6
b1110 1
b1110 ,
0(
#3870000
b100010 7
b1110 2
b1110 -
1(
#3880000
b1111 ,
b1111 1
b100011 6
0(
#3890000
1#
1$
b1111 -
b1111 2
b100011 7
1(
#3900000
b100100 6
b10000 1
b10000 ,
0(
#3910000
0#
19
b100100 7
b10000 2
b10000 -
1(
#3920000
b10001 ,
b10001 1
b100101 6
0(
#3930000
b10001 -
b10001 2
b100101 7
1(
#3940000
b100110 6
b10010 1
b10010 ,
0(
#3950000
b100110 7
b10010 2
b10010 -
1(
#3960000
b10011 ,
b10011 1
b100111 6
0(
#3970000
b10011 -
b10011 2
b100111 7
1(
#3980000
b0 6
b10100 1
b0 ,
0(
#3990000
0"
0&
b0 7
b10100 2
b0 -
1(
#4000000
b1 ,
b10101 1
b1 6
0(
#4010000
b1 -
b10101 2
b1 7
08
0:
1(
#4020000
b10 6
b10110 1
b10 ,
0(
#4030000
b10 7
b10110 2
b10 -
1(
#4040000
b11 ,
b10111 1
b11 6
0(
#4050000
b11 -
b10111 2
b11 7
1(
#4060000
b100 6
b11000 1
b100 ,
0(
#4070000
b100 7
b11000 2
b100 -
1(
#4080000
b101 ,
b11001 1
b101 6
0(
#4090000
b101 -
b11001 2
b101 7
1(
#4100000
b110 6
b11010 1
b110 ,
0(
#4110000
b110 7
b11010 2
b110 -
1(
#4120000
b111 ,
b11011 1
b111 6
0(
#4130000
b111 -
b11011 2
b111 7
1(
#4140000
b1000 6
b11100 1
b1000 ,
0(
#4150000
b1000 7
b11100 2
b1000 -
1(
#4160000
b1001 ,
b11101 1
b1001 6
0(
#4170000
b1001 -
b11101 2
b1001 7
1(
#4180000
b1010 6
b0 1
b1010 ,
0(
#4190000
1%
0$
1&
b1010 7
b0 2
b1010 -
1(
#4200000
b1011 ,
b1 1
b1011 6
0(
#4210000
0%
b1011 -
b1 2
b1011 7
18
09
1(
#4220000
b1100 6
b10 1
b1100 ,
0(
#4230000
b1100 7
b10 2
b1100 -
1(
#4240000
b1101 ,
b11 1
b1101 6
0(
#4250000
b1101 -
b11 2
b1101 7
1(
#4260000
b1110 6
b100 1
b1110 ,
0(
#4270000
b1110 7
b100 2
b1110 -
1(
#4280000
b1111 ,
b101 1
b1111 6
0(
#4290000
b1111 -
b101 2
b1111 7
1(
#4300000
b10000 6
b110 1
b10000 ,
0(
#4310000
b10000 7
b110 2
b10000 -
1(
#4320000
b10001 ,
b111 1
b10001 6
0(
#4330000
b10001 -
b111 2
b10001 7
1(
#4340000
b10010 6
b1000 1
b10010 ,
0(
#4350000
b10010 7
b1000 2
b10010 -
1(
#4360000
b10011 ,
b1001 1
b10011 6
0(
#4370000
b10011 -
b1001 2
b10011 7
1(
#4380000
b10100 6
b1010 1
b0 ,
0(
#4390000
1!
1"
0&
b10100 7
b1010 2
b0 -
1(
#4400000
b1 ,
b1011 1
b10101 6
0(
#4410000
0!
b1 -
b1011 2
b10101 7
08
1:
1(
#4420000
b10110 6
b1100 1
b10 ,
0(
#4430000
b10110 7
b1100 2
b10 -
1(
#4440000
b11 ,
b1101 1
b10111 6
0(
#4450000
b11 -
b1101 2
b10111 7
1(
#4460000
b11000 6
b1110 1
b100 ,
0(
#4470000
b11000 7
b1110 2
b100 -
1(
#4480000
b101 ,
b1111 1
b11001 6
0(
#4490000
1#
1$
b101 -
b1111 2
b11001 7
1(
#4500000
b11010 6
b10000 1
b110 ,
0(
#4510000
0#
19
b11010 7
b10000 2
b110 -
1(
#4520000
b111 ,
b10001 1
b11011 6
0(
#4530000
b111 -
b10001 2
b11011 7
1(
#4540000
b11100 6
b10010 1
b1000 ,
0(
#4550000
b11100 7
b10010 2
b1000 -
1(
#4560000
b1001 ,
b10011 1
b11101 6
0(
#4570000
b1001 -
b10011 2
b11101 7
1(
#4580000
b11110 6
b10100 1
b1010 ,
0(
#4590000
1%
1&
b11110 7
b10100 2
b1010 -
1(
#4600000
b1011 ,
b10101 1
b11111 6
0(
#4610000
0%
b1011 -
b10101 2
b11111 7
18
1(
#4620000
b100000 6
b10110 1
b1100 ,
0(
#4630000
b100000 7
b10110 2
b1100 -
1(
#4640000
b1101 ,
b10111 1
b100001 6
0(
#4650000
b1101 -
b10111 2
b100001 7
1(
#4660000
b100010 6
b11000 1
b1110 ,
0(
#4670000
b100010 7
b11000 2
b1110 -
1(
#4680000
b1111 ,
b11001 1
b100011 6
0(
#4690000
b1111 -
b11001 2
b100011 7
1(
#4700000
b100100 6
b11010 1
b10000 ,
0(
#4710000
b100100 7
b11010 2
b10000 -
1(
#4720000
b10001 ,
b11011 1
b100101 6
0(
#4730000
b10001 -
b11011 2
b100101 7
1(
#4740000
b100110 6
b11100 1
b10010 ,
0(
#4750000
b100110 7
b11100 2
b10010 -
1(
#4760000
b10011 ,
b11101 1
b100111 6
0(
