common/frqdivmod.v
module frqdivmod(clk, signal_out);
parameter DIV=2;
// calculated parameters
parameter WITH = ($clog2(DIV+1)>0) ? $clog2(DIV+1) : 1;

input wire clk;
output wire signal_out;

reg clk_n; 

reg [(WITH-1):0] pos_cnt; 
reg [(WITH-1):0] neg_cnt; 

wire [(WITH-1):0] div_value = DIV[(WITH-1):0];

initial begin
	clk_n <= 1'b0;
	pos_cnt <= {(WITH){1'b0}};
	neg_cnt <= {(WITH){1'b0}};
end

assign signal_out = (DIV==1) ? clk : clk_n;

always @ (posedge clk) begin
	pos_cnt <= (pos_cnt + 1'b1) % div_value;
end

always @ (negedge clk) begin
	neg_cnt <= (neg_cnt + 1'b1) % div_value;
end

always @(clk, pos_cnt, neg_cnt) begin //pos_cnt in sens list addd for resolve warning "variable is read inside the Always Construct but isn't in the Always Construct's Event Control"
	if ((DIV%2) == 1'b0) begin
		clk_n <= ( pos_cnt >= (DIV/2)) ? 1'b1 : 1'b0;
	end else begin
		clk_n <= (( pos_cnt > (DIV/2)) || ( neg_cnt > (DIV/2))) ? 1'b1 : 1'b0;
	end
end
	
endmodule

common/frqdivmod_test/testbench.v
`timescale 1us / 1ns

module testbench();
  parameter TEST_DURATION = 1000000;

  wire rst;
  wire signal_out_2;
  wire signal_out_3;
  wire signal_out_4;

  reg clk50M;
  initial clk50M <= 0;
  always
    #10 clk50M <= ~clk50M; // Задержка 10 ns (100mhz -  50 mhz clk)

  frqdivmod #(.DIV(2)) frqdivmod_2(
    .clk(clk50M),
    .signal_out(signal_out_2)
  );

  frqdivmod #(.DIV(3)) frqdivmod_3(
    .clk(clk50M),
    .signal_out(signal_out_3)
  );

  frqdivmod #(.DIV(4)) frqdivmod_4(
    .clk(clk50M),
    .signal_out(signal_out_4)
  );

  initial
  begin
    $dumpfile("out.vcd");
    $dumpvars(0,testbench);

    #TEST_DURATION;
    $display("test completed.");
    $finish;
  end
endmodule

common/frqdivmod_test/out.vcd
$date
	Thu Nov  7 00:40:26 2024
$end
$version
	Icarus Verilog
$end
$timescale
	1ns
$end
$scope module testbench $end
$var wire 1 ! signal_out_4 $end
$var wire 1 " signal_out_3 $end
$var wire 1 # signal_out_2 $end
$var parameter 32 $ TEST_DURATION $end
$var reg 1 % clk50M $end
$scope module frqdivmod_2 $end
$var wire 1 % clk $end
$var wire 2 & div_value [1:0] $end
$var wire 1 # signal_out $end
$var parameter 32 ' DIV $end
$var parameter 32 ( WITH $end
$var reg 1 ) clk_n $end
$var reg 2 * neg_cnt [1:0] $end
$var reg 2 + pos_cnt [1:0] $end
$upscope $end
$scope module frqdivmod_3 $end
$var wire 1 % clk $end
$var wire 2 , div_value [1:0] $end
$var wire 1 " signal_out $end
$var parameter 32 - DIV $end
$var parameter 32 . WITH $end
$var reg 1 / clk_n $end
$var reg 2 0 neg_cnt [1:0] $end
$var reg 2 1 pos_cnt [1:0] $end
$upscope $end
$scope module frqdivmod_4 $end
$var wire 1 % clk $end
$var wire 3 2 div_value [2:0] $end
$var wire 1 ! signal_out $end
$var parameter 32 3 DIV $end
$var parameter 32 4 WITH $end
$var reg 1 5 clk_n $end
$var reg 3 6 neg_cnt [2:0] $end
$var reg 3 7 pos_cnt [2:0] $end
$upscope $end
$upscope $end
$enddefinitions $end
$comment Show the parameter values. $end
$dumpall
b11 4
b100 3
b10 .
b11 -
b10 (
b10 '
b11110100001001000000 $
$end
#0
$dumpvars
b0 7
b1 6
05
b100 2
b0 1
b1 0
0/
b11 ,
b0 +
b1 *
0)
b10 &
0%
0#
0"
0!
$end
#10000
1#
1)
b1 +
b1 1
b1 7
1%
#20000
1"
1/
b10 6
b10 0
b0 *
0%
#30000
1!
15
0#
0)
b10 7
b10 1
b0 +
1%
#40000
b1 *
b0 0
b11 6
0%
#50000
1#
1)
0"
0/
b1 +
b0 1
b11 7
1%
#60000
b0 6
b1 0
b0 *
0%
#70000
0!
05
0#
0)
b0 7
b1 1
b0 +
1%
#80000
1"
1/
b1 *
b10 0
b1 6
0%
#90000
1#
1)
b1 +
b10 1
b1 7
1%
#100000
b10 6
b0 0
b0 *
0%
#110000
1!
15
0"
0/
0#
0)
b10 7
b0 1
b0 +
1%
#120000
b1 *
b1 0
b11 6
0%
#130000
1#
1)
b1 +
b1 1
b11 7
1%
#140000
1"
1/
b0 6
b10 0
b0 *
0%
#150000
0!
05
0#
0)
b0 7
b10 1
b0 +
1%
#160000
b1 *
b0 0
b1 6
0%
#170000
1#
1)
0"
0/
b1 +
b0 1
b1 7
1%
#180000
b10 6
b1 0
b0 *
0%
#190000
1!
15
0#
0)
b10 7
b1 1
b0 +
1%
#200000
1"
1/
b1 *
b10 0
b11 6
0%
#210000
1#
1)
b1 +
b10 1
b11 7
1%
#220000
b0 6
b0 0
b0 *
0%
#230000
0!
05
0"
0/
0#
0)
b0 7
b0 1
b0 +
1%
#240000
b1 *
b1 0
b1 6
0%
#250000
1#
1)
b1 +
b1 1
b1 7
1%
#260000
1"
1/
b10 6
b10 0
b0 *
0%
#270000
1!
15
0#
0)
b10 7
b10 1
b0 +
1%
#280000
b1 *
b0 0
b11 6
0%
#290000
1#
1)
0"
0/
b1 +
b0 1
b11 7
1%
#300000
b0 6
b1 0
b0 *
0%
#310000
0!
05
0#
0)
b0 7
b1 1
b0 +
1%
#320000
1"
1/
b1 *
b10 0
b1 6
0%
#330000
1#
1)
b1 +
b10 1
b1 7
1%
#340000
b10 6
b0 0
b0 *
0%
#350000
1!
15
0"
0/
0#
0)
b10 7
b0 1
b0 +
1%
#360000
b1 *
b1 0
b11 6
0%
#370000
1#
1)
b1 +
b1 1
b11 7
1%
#380000
1"
1/
b0 6
b10 0
b0 *
0%
#390000
0!
05
0#
0)
b0 7
b10 1
b0 +
1%
#400000
b1 *
b0 0
b1 6
0%
#410000
1#
1)
0"
0/
b1 +
b0 1
b1 7
1%
#420000
b10 6
b1 0
b0 *
0%
#430000
1!
15
0#
0)
b10 7
b1 1
b0 +
1%
#440000
1"
1/
b1 *
b10 0
b11 6
0%
#450000
1#
1)
b1 +
b10 1
b11 7
1%
#460000
b0 6
b0 0
b0 *
0%
#470000
0!
05
0"
0/
0#
0)
b0 7
b0 1
b0 +
1%
#480000
b1 *
b1 0
b1 6
0%
#490000
1#
1)
b1 +
b1 1
b1 7
1%
#500000
1"
1/
b10 6
b10 0
b0 *
0%
#510000
1!
15
0#
0)
b10 7
b10 1
b0 +
1%
#520000
b1 *
b0 0
b11 6
0%
#530000
1#
1)
0"
0/
b1 +
b0 1
b11 7
1%
#540000
b0 6
b1 0
b0 *
0%
#550000
0!
05
0#
0)
b0 7
b1 1
b0 +
1%
#560000
1"
1/
b1 *
b10 0
b1 6
0%
#570000
1#
1)
b1 +
b10 1
b1 7
1%
#580000
b10 6
b0 0
b0 *
0%
#590000
1!
15
0"
0/
0#
0)
b10 7
b0 1
b0 +
1%
#600000
b1 *
b1 0
b11 6
0%
#610000
1#
1)
b1 +
b1 1
b11 7
1%
#620000
1"
1/
b0 6
b10 0
b0 *
0%
#630000
0!
05
0#
0)
b0 7
b10 1
b0 +
1%
#640000
b1 *
b0 0
b1 6
0%
#650000
1#
1)
0"
0/
b1 +
b0 1
b1 7
1%
#660000
b10 6
b1 0
b0 *
0%
#670000
1!
15
0#
0)
b10 7
b1 1
b0 +
1%
#680000
1"
1/
b1 *
b10 0
b11 6
0%
#690000
1#
1)
b1 +
b10 1
b11 7
1%
#700000
b0 6
b0 0
b0 *
0%
#710000
0!
05
0"
0/
0#
0)
b0 7
b0 1
b0 +
1%
#720000
b1 *
b1 0
b1 6
0%
#730000
1#
1)
b1 +
b1 1
b1 7
1%
#740000
1"
1/
b10 6
b10 0
b0 *
0%
#750000
1!
15
0#
0)
b10 7
b10 1
b0 +
1%
#760000
b1 *
b0 0
b11 6
0%
#770000
1#
1)
0"
0/
b1 +
b0 1
b11 7
1%
#780000
b0 6
b1 0
b0 *
0%
#790000
0!
05
0#
0)
b0 7
b1 1
b0 +
1%
#800000
1"
1/
b1 *
b10 0
b1 6
0%
#810000
1#
1)
b1 +
b10 1
b1 7
1%
#820000
b10 6
b0 0
b0 *
0%
#830000
1!
15
0"
0/
0#
0)
b10 7
b0 1
b0 +
1%
#840000
b1 *
b1 0
b11 6
0%
#850000
1#
1)
b1 +
b1 1
b11 7
1%
#860000
1"
1/
b0 6
b10 0
b0 *
0%
#870000
0!
05
0#
0)
b0 7
b10 1
b0 +
1%
#880000
b1 *
b0 0
b1 6
0%
#890000
1#
1)
0"
0/
b1 +
b0 1
b1 7
1%
#900000
b10 6
b1 0
b0 *
0%
#910000
1!
15
0#
0)
b10 7
b1 1
b0 +
1%
#920000
1"
1/
b1 *
b10 0
b11 6
0%
#930000
1#
1)
b1 +
b10 1
b11 7
1%
#940000
b0 6
b0 0
b0 *
0%
#950000
0!
05
0"
0/
0#
0)
b0 7
b0 1
b0 +
1%
#960000
b1 *
b1 0
b1 6
0%
#970000
1#
1)
b1 +
b1 1
b1 7
1%
#980000
1"
1/
b10 6
b10 0
b0 *
0%
#990000
1!
15
0#
0)
b10 7
b10 1
b0 +
1%
#1000000
b1 *
b0 0
b11 6
0%
#1010000
1#
1)
0"
0/
b1 +
b0 1
b11 7
1%
#1020000
b0 6
b1 0
b0 *
0%
#1030000
0!
05
0#
0)
b0 7
b1 1
b0 +
1%
#1040000
1"
1/
b1 *
b10 0
b1 6
0%
#1050000
1#
1)
b1 +
b10 1
b1 7
1%
#1060000
b10 6
b0 0
b0 *
0%
#1070000
1!
15
0"
0/
0#
0)
b10 7
b0 1
b0 +
1%
#1080000
b1 *
b1 0
b11 6
0%
#1090000
1#
1)
b1 +
b1 1
b11 7
1%
#1100000
1"
1/
b0 6
b10 0
b0 *
0%
#1110000
0!
05
0#
0)
b0 7
b10 1
b0 +
1%
#1120000
b1 *
b0 0
b1 6
0%
#1130000
1#
1)
0"
0/
b1 +
b0 1
b1 7
1%
#1140000
b10 6
b1 0
b0 *
0%
#1150000
1!
15
0#
0)
b10 7
b1 1
b0 +
1%
#1160000
1"
1/
b1 *
b10 0
b11 6
0%
#1170000
1#
1)
b1 +
b10 1
b11 7
1%
#1180000
b0 6
b0 0
b0 *
0%
#1190000
0!
05
0"
0/
0#
0)
b0 7
b0 1
b0 +
1%
#1200000
b1 *
b1 0
b1 6
0%
#1210000
1#
1)
b1 +
b1 1
b1 7
1%
#1220000
1"
1/
b10 6
b10 0
b0 *
0%
#1230000
1!
15
0#
0)
b10 7
b10 1
b0 +
1%
#1240000
b1 *
b0 0
b11 6
0%
#1250000
1#
1)
0"
0/
b1 +
b0 1
b11 7
1%
#1260000
b0 6
b1 0
b0 *
0%
#1270000
0!
05
0#
0)
b0 7
b1 1
b0 +
1%
#1280000
1"
1/
b1 *
b10 0
b1 6
0%
#1290000
1#
1)
b1 +
b10 1
b1 7
1%
#1300000
b10 6
b0 0
b0 *
0%
#1310000
1!
15
0"
0/
0#
0)
b10 7
b0 1
b0 +
1%
#1320000
b1 *
b1 0
b11 6
0%
#1330000
1#
1)
b1 +
b1 1
b11 7
1%
#1340000
1"
1/
b0 6
b10 0
b0 *
0%
#1350000
0!
05
0#
0)
b0 7
b10 1
b0 +
1%
#1360000
b1 *
b0 0
b1 6
0%
#1370000
1#
1)
0"
0/
b1 +
b0 1
b1 7
1%
#1380000
b10 6
b1 0
b0 *
0%
#1390000
1!
15
0#
0)
b10 7
b1 1
b0 +
1%
#1400000
1"
1/
b1 *
b10 0
b11 6
0%
#1410000
1#
1)
b1 +
b10 1
b11 7
1%
#1420000
b0 6
b0 0
b0 *
0%
#1430000
0!
05
0"
0/
0#
0)
b0 7
b0 1
b0 +
1%
#1440000
b1 *
b1 0
b1 6
0%
#1450000
1#
1)
b1 +
b1 1
b1 7
1%
#1460000
1"
1/
b10 6
b10 0
b0 *
0%
#1470000
1!
15
0#
0)
b10 7
b10 1
b0 +
1%
#1480000
b1 *
b0 0
b11 6
0%
#1490000
1#
1)
0"
0/
b1 +
b0 1
b11 7
1%
#1500000
b0 6
b1 0
b0 *
0%
#1510000
0!
05
0#
0)
b0 7
b1 1
b0 +
1%
#1520000
1"
1/
b1 *
b10 0
b1 6
0%
#1530000
1#
1)
b1 +
b10 1
b1 7
1%
#1540000
b10 6
b0 0
b0 *
0%
#1550000
1!
15
0"
0/
0#
0)
b10 7
b0 1
b0 +
1%
#1560000
b1 *
b1 0
b11 6
0%
#1570000
1#
1)
b1 +
b1 1
b11 7
1%
#1580000
1"
1/
b0 6
b10 0
b0 *
0%
#1590000
0!
05
0#
0)
b0 7
b10 1
b0 +
1%
#1600000
b1 *
b0 0
b1 6
0%
#1610000
1#
1)
0"
0/
b1 +
b0 1
b1 7
1%
#1620000
b10 6
b1 0
b0 *
0%
#1630000
1!
15
0#
0)
b10 7
b1 1
b0 +
1%
#1640000
1"
1/
b1 *
b10 0
b11 6
0%
#1650000
1#
1)
b1 +
b10 1
b11 7
1%
#1660000
b0 6
b0 0
b0 *
0%
#1670000
0!
05
0"
0/
0#
0)
b0 7
b0 1
b0 +
1%
#1680000
b1 *
b1 0
b1 6
0%
#1690000
1#
1)
b1 +
b1 1
b1 7
1%
#1700000
1"
1/
b10 6
b10 0
b0 *
0%
#1710000
1!
15
0#
0)
b10 7
b10 1
b0 +
1%
#1720000
b1 *
b0 0
b11 6
0%
#1730000
1#
1)
0"
0/
b1 +
b0 1
b11 7
1%
#1740000
b0 6
b1 0
b0 *
0%
#1750000
0!
05
0#
0)
b0 7
b1 1
b0 +
1%
#1760000
1"
1/
b1 *
b10 0
b1 6
0%
#1770000
1#
1)
b1 +
b10 1
b1 7
1%
#1780000
b10 6
b0 0
b0 *
0%
#1790000
1!
15
0"
0/
0#
0)
b10 7
b0 1
b0 +
1%
#1800000
b1 *
b1 0
b11 6
0%
#1810000
1#
1)
b1 +
b1 1
b11 7
1%
#1820000
1"
1/
b0 6
b10 0
b0 *
0%
#1830000
0!
05
0#
0)
b0 7
b10 1
b0 +
1%
#1840000
b1 *
b0 0
b1 6
0%
#1850000
1#
1)
0"
0/
b1 +
b0 1
b1 7
1%
#1860000
b10 6
b1 0
b0 *
0%
#1870000
1!
15
0#
0)
b10 7
b1 1
b0 +
1%
#1880000
1"
1/
b1 *
b10 0
b11 6
0%
#1890000
1#
1)
b1 +
b10 1
b11 7
1%
#1900000
b0 6
b0 0
b0 *
0%
#1910000
0!
05
0"
0/
0#
0)
b0 7
b0 1
b0 +
1%
#1920000
b1 *
b1 0
b1 6
0%
#1930000
1#
1)
b1 +
b1 1
b1 7
1%
#1940000
1"
1/
b10 6
b10 0
b0 *
0%
#1950000
1!
15
0#
0)
b10 7
b10 1
b0 +
1%
#1960000
b1 *
b0 0
b11 6
0%
#1970000
1#
1)
0"
0/
b1 +
b0 1
b11 7
1%
#1980000
b0 6
b1 0
b0 *
0%
#1990000
0!
05
0#
0)
b0 7
b1 1
b0 +
1%
#2000000
1"
1/
b1 *
b10 0
b1 6
0%
#2010000
1#
1)
b1 +
b10 1
b1 7
1%
#2020000
b10 6
b0 0
b0 *
0%
#2030000
1!
15
0"
0/
0#
0)
b10 7
b0 1
b0 +
1%
#2040000
b1 *
b1 0
b11 6
0%
#2050000
1#
1)
b1 +
b1 1
b11 7
1%
#2060000
1"
1/
b0 6
b10 0
b0 *
0%
#2070000
0!
05
0#
0)
b0 7
b10 1
b0 +
1%
#2080000
b1 *
b0 0
b1 6
0%
#2090000
1#
1)
0"
0/
b1 +
b0 1
b1 7
1%
#2100000
b10 6
b1 0
b0 *
0%
#2110000
1!
15
0#
0)
b10 7
b1 1
b0 +
1%
#2120000
1"
1/
b1 *
b10 0
b11 6
0%
#2130000
1#
1)
b1 +
b10 1
b11 7
1%
#2140000
b0 6
b0 0
b0 *
0%
#2150000
0!
05
0"
0/
0#
0)
b0 7
b0 1
b0 +
1%
#2160000
b1 *
b1 0
b1 6
0%
#2170000
1#
1)
b1 +
b1 1
b1 7
1%
#2180000
1"
1/
b10 6
b10 0
b0 *
0%
#2190000
1!
15
0#
0)
b10 7
b10 1
b0 +
1%
#2200000
b1 *
b0 0
b11 6
0%
#2210000
1#
1)
0"
0/
b1 +
b0 1
b11 7
1%
#2220000
b0 6
b1 0
b0 *
0%
#2230000
0!
05
0#
0)
b0 7
b1 1
b0 +
1%
#2240000
1"
1/
b1 *
b10 0
b1 6
0%
#2250000
1#
1)
b1 +
b10 1
b1 7
1%
#2260000
b10 6
b0 0
b0 *
0%
#2270000
1!
15
0"
0/
0#
0)
b10 7
b0 1
b0 +
1%
#2280000
b1 *
b1 0
b11 6
0%
#2290000
1#
1)
b1 +
b1 1
b11 7
1%
#2300000
1"
1/
b0 6
b10 0
b0 *
0%
#2310000
0!
05
0#
0)
b0 7
b10 1
b0 +
1%
#2320000
b1 *
b0 0
b1 6
0%
#2330000
1#
1)
0"
0/
b1 +
b0 1
b1 7
1%
#2340000
b10 6
b1 0
b0 *
0%
#2350000
1!
15
0#
0)
b10 7
b1 1
b0 +
1%
#2360000
1"
1/
b1 *
b10 0
b11 6
0%
#2370000
1#
1)
b1 +
b10 1
b11 7
1%
#2380000
b0 6
b0 0
b0 *
0%
#2390000
0!
05
0"
0/
0#
0)
b0 7
b0 1
b0 +
1%
#2400000
b1 *
b1 0
b1 6
0%
#2410000
1#
1)
b1 +
b1 1
b1 7
1%
#2420000
1"
1/
b10 6
b10 0
b0 *
0%
#2430000
1!
15
0#
0)
b10 7
b10 1
b0 +
1%
#2440000
b1 *
b0 0
b11 6
0%
#2450000
1#
1)
0"
0/
b1 +
b0 1
b11 7
1%
#2460000
b0 6
b1 0
b0 *
0%
#2470000
0!
05
0#
0)
b0 7
b1 1
b0 +
1%
#2480000
1"
1/
b1 *
b10 0
b1 6
0%
#2490000
1#
1)
b1 +
b10 1
b1 7
1%
#2500000
b10 6
b0 0
b0 *
0%
#2510000
1!
15
0"
0/
0#
0)
b10 7
b0 1
b0 +
1%
#2520000
b1 *
b1 0
b11 6
0%
#2530000
1#
1)
b1 +
b1 1
b11 7
1%
#2540000
1"
1/
b0 6
b10 0
b0 *
0%
#2550000
0!
05
0#
0)
b0 7
b10 1
b0 +
1%
#2560000
b1 *
b0 0
b1 6
0%
#2570000
1#
1)
0"
0/
b1 +
b0 1
b1 7
1%
#2580000
b10 6
b1 0
b0 *
0%
#2590000
1!
15
0#
0)
b10 7
b1 1
b0 +
1%
#2600000
1"
1/
b1 *
b10 0
b11 6
0%
#2610000
1#
1)
b1 +
b10 1
b11 7
1%
#2620000
b0 6
b0 0
b0 *
0%
#2630000
0!
05
0"
0/
0#
0)
b0 7
b0 1
b0 +
1%
#2640000
b1 *
b1 0
b1 6
0%
#2650000
1#
1)
b1 +
b1 1
b1 7
1%
#2660000
1"
1/
b10 6
b10 0
b0 *
0%
#2670000
1!
15
0#
0)
b10 7
b10 1
b0 +
1%
#2680000
b1 *
b0 0
b11 6
0%
#2690000
1#
1)
0"
0/
b1 +
b0 1
b11 7
1%
#2700000
b0 6
b1 0
b0 *
0%
#2710000
0!
05
0#
0)
b0 7
b1 1
b0 +
1%
#2720000
1"
1/
b1 *
b10 0
b1 6
0%
#2730000
1#
1)
b1 +
b10 1
b1 7
1%
#2740000
b10 6
b0 0
b0 *
0%
#2750000
1!
15
0"
0/
0#
0)
b10 7
b0 1
b0 +
1%
#2760000
b1 *
b1 0
b11 6
0%
#2770000
1#
1)
b1 +
b1 1
b11 7
1%
#2780000
1"
1/
b0 6
b10 0
b0 *
0%
#2790000
0!
05
0#
0)
b0 7
b10 1
b0 +
1%
#2800000
b1 *
b0 0
b1 6
0%
#2810000
1#
1)
0"
0/
b1 +
b0 1
b1 7
1%
#2820000
b10 6
b1 0
b0 *
0%
#2830000
1!
15
0#
0)
b10 7
b1 1
b0 +
1%
#2840000
1"
1/
b1 *
b10 0
b11 6
0%
#2850000
1#
1)
b1 +
b10 1
b11 7
1%
#2860000
b0 6
b0 0
b0 *
0%
#2870000
0!
05
0"
0/
0#
0)
b0 7
b0 1
b0 +
1%
#2880000
b1 *
b1 0
b1 6
0%
#2890000
1#
1)
b1 +
b1 1
b1 7
1%
#2900000
1"
1/
b10 6
b10 0
b0 *
0%
#2910000
1!
15
0#
0)
b10 7
b10 1
b0 +
1%
#2920000
b1 *
b0 0
b11 6
0%
#2930000
1#
1)
0"
0/
b1 +
b0 1
b11 7
1%
#2940000
b0 6
b1 0
b0 *
0%
#2950000
0!
05
0#
0)
b0 7
b1 1
b0 +
1%
#2960000
1"
1/
b1 *
b10 0
b1 6
0%
#2970000
1#
1)
b1 +
b10 1
b1 7
1%
#2980000
b10 6
b0 0
b0 *
0%
#2990000
1!
15
0"
0/
0#
0)
b10 7
b0 1
b0 +
1%
#3000000
b1 *
b1 0
b11 6
0%
#3010000
1#
1)
b1 +
b1 1
b11 7
1%
#3020000
1"
1/
b0 6
b10 0
b0 *
0%
#3030000
0!
05
0#
0)
b0 7
b10 1
b0 +
1%
#3040000
b1 *
b0 0
b1 6
0%
#3050000
1#
1)
0"
0/
b1 +
b0 1
b1 7
1%
#3060000
b10 6
b1 0
b0 *
0%
#3070000
1!
15
0#
0)
b10 7
b1 1
b0 +
1%
#3080000
1"
1/
b1 *
b10 0
b11 6
0%
#3090000
1#
1)
b1 +
b10 1
b11 7
1%
#3100000
b0 6
b0 0
b0 *
0%
#3110000
0!
05
0"
0/
0#
0)
b0 7
b0 1
b0 +
1%
#3120000
b1 *
b1 0
b1 6
0%
#3130000
1#
1)
b1 +
b1 1
b1 7
1%
#3140000
1"
1/
b10 6
b10 0
b0 *
0%
#3150000
1!
15
0#
0)
b10 7
b10 1
b0 +
1%
#3160000
b1 *
b0 0
b11 6
0%
#3170000
1#
1)
0"
0/
b1 +
b0 1
b11 7
1%
#3180000
b0 6
b1 0
b0 *
0%
#3190000
0!
05
0#
0)
b0 7
b1 1
b0 +
1%
#3200000
1"
1/
b1 *
b10 0
b1 6
0%
#3210000
1#
1)
b1 +
b10 1
b1 7
1%
#3220000
b10 6
b0 0
b0 *
0%
#3230000
1!
15
0"
0/
0#
0)
b10 7
b0 1
b0 +
1%
#3240000
b1 *
b1 0
b11 6
0%
#3250000
1#
1)
b1 +
b1 1
b11 7
1%
#3260000
1"
1/
b0 6
b10 0
b0 *
0%
#3270000
0!
05
0#
0)
b0 7
b10 1
b0 +
1%
#3280000
b1 *
b0 0
b1 6
0%
#3290000
1#
1)
0"
0/
b1 +
b0 1
b1 7
1%
#3300000
b10 6
b1 0
b0 *
0%
#3310000
1!
15
0#
0)
b10 7
b1 1
b0 +
1%
#3320000
1"
1/
b1 *
b10 0
b11 6
0%
#3330000
1#
1)
b1 +
b10 1
b11 7
1%
#3340000
b0 6
b0 0
b0 *
0%
#3350000
0!
05
0"
0/
0#
0)
b0 7
b0 1
b0 +
1%
#3360000
b1 *
b1 0
b1 6
0%
#3370000
1#
1)
b1 +
b1 1
b1 7
1%
#3380000
1"
1/
b10 6
b10 0
b0 *
0%
#3390000
1!
15
0#
0)
b10 7
b10 1
b0 +
1%
#3400000
b1 *
b0 0
b11 6
0%
#3410000
1#
1)
0"
0/
b1 +
b0 1
b11 7
1%
#3420000
b0 6
b1 0
b0 *
0%
#3430000
0!
05
0#
0)
b0 7
b1 1
b0 +
1%
#3440000
1"
1/
b1 *
b10 0
b1 6
0%
#3450000
1#
1)
b1 +
b10 1
b1 7
1%
#3460000
b10 6
b0 0
b0 *
0%
#3470000
1!
15
0"
0/
0#
0)
b10 7
b0 1
b0 +
1%
#3480000
b1 *
b1 0
b11 6
0%
#3490000
1#
1)
b1 +
b1 1
b11 7
1%
#3500000
1"
1/
b0 6
b10 0
b0 *
0%
#3510000
0!
05
0#
0)
b0 7
b10 1
b0 +
1%
#3520000
b1 *
b0 0
b1 6
0%
#3530000
1#
1)
0"
0/
b1 +
b0 1
b1 7
1%
#3540000
b10 6
b1 0
b0 *
0%
#3550000
1!
15
0#
0)
b10 7
b1 1
b0 +
1%
#3560000
1"
1/
b1 *
b10 0
b11 6
0%
#3570000
1#
1)
b1 +
b10 1
b11 7
1%
#3580000
b0 6
b0 0
b0 *
0%
#3590000
0!
05
0"
0/
0#
0)
b0 7
b0 1
b0 +
1%
#3600000
b1 *
b1 0
b1 6
0%
#3610000
1#
1)
b1 +
b1 1
b1 7
1%
#3620000
1"
1/
b10 6
b10 0
b0 *
0%
#3630000
1!
15
0#
0)
b10 7
b10 1
b0 +
1%
#3640000
b1 *
b0 0
b11 6
0%
#3650000
1#
1)
0"
0/
b1 +
b0 1
b11 7
1%
#3660000
b0 6
b1 0
b0 *
0%
#3670000
0!
05
0#
0)
b0 7
b1 1
b0 +
1%
#3680000
1"
1/
b1 *
b10 0
b1 6
0%
#3690000
1#
1)
b1 +
b10 1
b1 7
1%
#3700000
b10 6
b0 0
b0 *
0%
#3710000
1!
15
0"
0/
0#
0)
b10 7
b0 1
b0 +
1%
#3720000
b1 *
b1 0
b11 6
0%
#3730000
1#
1)
b1 +
b1 1
b11 7
1%
#3740000
1"
1/
b0 6
b10 0
b0 *
0%
#3750000
0!
05
0#
0)
b0 7
b10 1
b0 +
1%
#3760000
b1 *
b0 0
b1 6
0%
#3770000
1#
1)
0"
0/
b1 +
b0 1
b1 7
1%
#3780000
b10 6
b1 0
b0 *
0%
#3790000
1!
15
0#
0)
b10 7
b1 1
b0 +
1%
#3800000
1"
1/
b1 *
b10 0
b11 6
0%
#3810000
1#
1)
b1 +
b10 1
b11 7
1%
#3820000
b0 6
b0 0
b0 *
0%
#3830000
0!
05
0"
0/
0#
0)
b0 7
b0 1
b0 +
1%
#3840000
b1 *
b1 0
b1 6
0%
#3850000
1#
1)
b1 +
b1 1
b1 7
1%
#3860000
1"
1/
b10 6
b10 0
b0 *
0%
#3870000
1!
15
0#
0)
b10 7
b10 1
b0 +
1%
#3880000
b1 *
b0 0
b11 6
0%
#3890000
1#
1)
0"
0/
b1 +
b0 1
b11 7
1%
#3900000
b0 6
b1 0
b0 *
0%
#3910000
0!
05
0#
0)
b0 7
b1 1
b0 +
1%
#3920000
1"
1/
b1 *
b10 0
b1 6
0%
#3930000
1#
1)
b1 +
b10 1
b1 7
1%
#3940000
b10 6
b0 0
b0 *
0%
#3950000
1!
15
0"
0/
0#
0)
b10 7
b0 1
b0 +
1%
#3960000
b1 *
b1 0
b11 6
0%
#3970000
1#
1)
b1 +
b1 1
b11 7
1%
#3980000
1"
1/
b0 6
b10 0
b0 *
0%
#3990000
0!
05
0#
0)
b0 7
b10 1
b0 +
1%
#4000000
b1 *
b0 0
b1 6
0%
#4010000
1#
1)
0"
0/
b1 +
b0 1
b1 7
1%
#4020000
b10 6
b1 0
b0 *
0%
#4030000
1!
15
0#
0)
b10 7
b1 1
b0 +
1%
#4040000
1"
1/
b1 *
b10 0
b11 6
0%
#4050000
1#
1)
b1 +
b10 1
b11 7
1%
#4060000
b0 6
b0 0
b0 *
0%
#4070000
0!
05
0"
0/
0#
0)
b0 7
b0 1
b0 +
1%
#4080000
b1 *
b1 0
b1 6
0%
#4090000
1#
1)
b1 +
b1 1
b1 7
1%
#4100000
1"
1/
b10 6
b10 0
b0 *
0%
#4110000
1!
15
0#
0)
b10 7
b10 1
b0 +
1%
#4120000
b1 *
b0 0
b11 6
0%
#4130000
1#
1)
0"
0/
b1 +
b0 1
b11 7
1%
#4140000
b0 6
b1 0
b0 *
0%
#4150000
0!
05
0#
0)
b0 7
b1 1
b0 +
1%
#4160000
1"
1/
b1 *
b10 0
b1 6
0%
#4170000
1#
1)
b1 +
b10 1
b1 7
1%
#4180000
b10 6
b0 0
b0 *
0%
#4190000
1!
15
0"
0/
0#
0)
b10 7
b0 1
b0 +
1%
#4200000
b1 *
b1 0
b11 6
0%
#4210000
1#
1)
b1 +
b1 1
b11 7
1%
#4220000
1"
1/
b0 6
b10 0
b0 *
0%
#4230000
0!
05
0#
0)
b0 7
b10 1
b0 +
1%
#4240000
b1 *
b0 0
b1 6
0%
#4250000
1#
1)
0"
0/
b1 +
b0 1
b1 7
1%
#4260000
b10 6
b1 0
b0 *
0%
#4270000
1!
15
0#
0)
b10 7
b1 1
b0 +
1%
#4280000
1"
1/
b1 *
b10 0
b11 6
0%
#4290000
1#
1)
b1 +
b10 1
b11 7
1%
#4300000
b0 6
b0 0
b0 *
0%
#4310000
0!
05
0"
0/
0#
0)
b0 7
b0 1
b0 +
1%
#4320000
b1 *
b1 0
b1 6
0%
#4330000
1#
1)
b1 +
b1 1
b1 7
1%
#4340000
1"
1/
b10 6
b10 0
b0 *
0%
#4350000
1!
15
0#
0)
b10 7
b10 1
b0 +
1%
#4360000
b1 *
b0 0
b11 6
0%
#4370000
1#
1)
0"
0/
b1 +
b0 1
b11 7
1%
#4380000
b0 6
b1 0
b0 *
0%
#4390000
0!
05
0#
0)
b0 7
b1 1
b0 +
1%
#4400000
1"
1/
b1 *
b10 0
b1 6
0%
#4410000
1#
1)
b1 +
b10 1
b1 7
1%
#4420000
b10 6
b0 0
b0 *
0%
#4430000
1!
15
0"
0/
0#
0)
b10 7
b0 1
b0 +
1%
#4440000
b1 *
b1 0
b11 6
0%
#4450000
1#
1)
b1 +
b1 1
b11 7
1%
#4460000
1"
1/
b0 6
b10 0
b0 *
0%
#4470000
0!
05
0#
0)
b0 7
b10 1
b0 +
1%
#4480000
b1 *
b0 0
b1 6
0%
#4490000
1#
1)
0"
0/
b1 +
b0 1
b1 7
1%
#4500000
b10 6
b1 0
b0 *
0%
#4510000
1!
15
0#
0)
b10 7
b1 1
b0 +
1%
#4520000
1"
1/
b1 *
b10 0
b11 6
0%
#4530000
1#
1)
b1 +
b10 1
b11 7
1%
#4540000
b0 6
b0 0
b0 *
0%
